dff.v
// ===========================================================================
//
// Description:
//  Verilog module sirv_gnrl DFF with Load-enable and Reset
//  Default reset value is 1
//
// ===========================================================================
module dfflrs # (
  parameter DW = 32
) (

  input               lden, 
  input      [DW-1:0] dnxt,
  output     [DW-1:0] qout,

  input               clk,
  input               rst_n
);

reg [DW-1:0] qout_r;

always @(posedge clk or negedge rst_n)
begin : DFFLRS_PROC
  if (rst_n == 1'b0)
    qout_r <= {DW{1'b1}};
  else if (lden == 1'b1)
    qout_r <= dnxt;
end

assign qout = qout_r;


endmodule
// ===========================================================================
//
// Description:
//  Verilog module sirv_gnrl DFF with Load-enable and Reset
//  Default reset value is 0
//
// ===========================================================================

module dfflr # (
  parameter DW = 32
) (

  input               lden, 
  input      [DW-1:0] dnxt,
  output     [DW-1:0] qout,

  input               clk,
  input               rst_n
);

reg [DW-1:0] qout_r;

always @(posedge clk or negedge rst_n)
begin : DFFLR_PROC
  if (rst_n == 1'b0)
    qout_r <= {DW{1'b0}};
  else if (lden == 1'b1)
    qout_r <= #1 dnxt;
end

assign qout = qout_r;


endmodule
// ===========================================================================
//
// Description:
//  Verilog module sirv_gnrl DFF with Load-enable, no reset 
//
// ===========================================================================

module dffl # (
  parameter DW = 32
) (

  input               lden, 
  input      [DW-1:0] dnxt,
  output     [DW-1:0] qout,

  input               clk 
);

reg [DW-1:0] qout_r;

always @(posedge clk)
begin : DFFL_PROC
  if (lden == 1'b1)
    qout_r <= #1 dnxt;
end

assign qout = qout_r;


endmodule
// ===========================================================================
//
// Description:
//  Verilog module sirv_gnrl DFF with Reset, no load-enable
//  Default reset value is 1
//
// ===========================================================================

module dffrs # (
  parameter DW = 32
) (

  input      [DW-1:0] dnxt,
  output     [DW-1:0] qout,

  input               clk,
  input               rst_n
);

reg [DW-1:0] qout_r;

always @(posedge clk or negedge rst_n)
begin : DFFRS_PROC
  if (rst_n == 1'b0)
    qout_r <= {DW{1'b1}};
  else                  
    qout_r <= dnxt;
end

assign qout = qout_r;

endmodule
// ===========================================================================
//
// Description:
//  Verilog module sirv_gnrl DFF with Reset, no load-enable
//  Default reset value is 0
//
// ===========================================================================

module dffr # (
  parameter DW = 32
) (

  input      [DW-1:0] dnxt,
  output     [DW-1:0] qout,

  input               clk,
  input               rst_n
);

reg [DW-1:0] qout_r;

always @(posedge clk or negedge rst_n)
begin : DFFR_PROC
  if (rst_n == 1'b0)
    qout_r <= {DW{1'b0}};
  else                  
    qout_r <= dnxt;
end

assign qout = qout_r;

endmodule
// ===========================================================================
//
// Description:
//  Verilog module for general latch 
//
// ===========================================================================

module sirv_gnrl_ltch # (
  parameter DW = 32
) (

  //input               test_mode,
  input               lden, 
  input      [DW-1:0] dnxt,
  output     [DW-1:0] qout
);

reg [DW-1:0] qout_r;

always @ (*) 
begin : LTCH_PROC
  if (lden == 1'b1)
    qout_r <= dnxt;
end

//assign qout = test_mode ? dnxt : qout_r;
assign qout = qout_r;


endmodule

timer.v
module timer # (
  parameter WIDTH = 16
) (
  input [WIDTH-1:0] set,
  input       load,
  output      irq,

  input clk,
  input rst_n
);

wire [WIDTH:0] cnt;
wire [WIDTH:0] cnt_next;
wire [WIDTH:0] cnt_next_or_load;
wire sign = cnt[WIDTH];

assign irq = cnt == 17'd0;

wire [WIDTH:0] set_ext;
assign set_ext = {1'b0, set};

assign cnt_next =
    ({(WIDTH+1){~sign}} & (cnt - 17'd1))
  | ({(WIDTH+1){ sign}} & 17'h1ffff);

assign cnt_next_or_load =
    ({(WIDTH+1){ load}} & set_ext)
  | ({(WIDTH+1){~load}} & cnt_next);

dffrs #(WIDTH+1) timer_dff (
  .dnxt(cnt_next_or_load),
  .qout(cnt),
  .clk(clk),
  .rst_n(rst_n)
);

endmodule

processor.v
module processor # (
  parameter OPCODE_WIDTH = 8,
  parameter REG_WIDTH = 8,
  parameter IMME_WIDTH = 16,
  parameter INSTRS_WIDTH = 32,
  parameter ADDR_WIDTH = 8
) (
  input                     ena,
  input  [INSTRS_WIDTH-1:0] instr,
  output   [ADDR_WIDTH-1:0] pc,

  output ctrl_fill,
  output ctrl_release,
  output ctrl_forward,
  output ctrl_reverse,

  input clk,
  input rst_n
);

localparam op_wait    = 8'h01;
localparam op_fill    = 8'h02;
localparam op_release = 8'h03;
localparam op_forward = 8'h04;
localparam op_reverse = 8'h05;
localparam op_set     = 8'h11;
localparam op_dec     = 8'h12;
localparam op_jz      = 8'h21;
localparam op_jnz     = 8'h22;

wire op_is_wait;
wire op_is_fill;
wire op_is_release;
wire op_is_forward;
wire op_is_reverse;
wire op_is_set;
wire op_is_dec;
wire op_is_jz;
wire op_is_jnz;

assign op_is_wait    = opcode == op_wait;
assign op_is_fill    = opcode == op_fill;
assign op_is_release = opcode == op_release;
assign op_is_forward = opcode == op_forward;
assign op_is_reverse = opcode == op_reverse;
assign op_is_set     = opcode == op_set;
assign op_is_dec     = opcode == op_dec;
assign op_is_jz      = opcode == op_jz;
assign op_is_jnz     = opcode == op_jnz;


wire [7:0] opcode;
wire [7:0] reg_id;
wire [15:0] arg;

assign opcode = instr[7:0];
assign reg_id = instr[15:8];
assign arg = instr[31:16];

wire sleep;
wire sleep_next;
wire sleep_instr;
wire sleep_exit_ena;
wire active_exit_ena;
wire keep_state;

assign sleep_instr =
  opcode[7:4] == 4'd0;
assign active_exit_ena =
  (~sleep) & sleep_instr;
assign sleep_exit_ena =
  sleep & irq;
assign keep_state =
  ~active_exit_ena & ~sleep_exit_ena;

assign sleep_next =
    (active_exit_ena & 1'b1)
  | (sleep_exit_ena  & 1'b0)
  | (keep_state      & sleep);

dffr #(1) sleep_dff (
  .dnxt(sleep_next),
  .qout(sleep),
  .clk(clk),
  .rst_n(rst_n)
);

wire [15:0] var;
wire [15:0] var_next;

assign ctrl_fill    = ~irq & op_is_fill;
assign ctrl_release = ~irq & op_is_release;
assign ctrl_forward = ~irq & op_is_forward;
assign ctrl_reverse = ~irq & op_is_reverse;

assign var_keep = ~op_is_set & ~op_is_dec;
assign var_next =
    ({16{op_is_set}} & arg)
  | ({16{op_is_dec}} & (var - 16'd1))
  | ({16{var_keep }} & var);

dffr #(16) var_dff (
  .dnxt(var_next),
  .qout(var),
  .clk(clk),
  .rst_n(rst_n)
);

wire [7:0] pc;
wire [7:0] pc_next;

wire fetch;
wire jump;
wire stay;

assign jump =
    (op_is_jz  & (var == 16'd0))
  | (op_is_jnz & (var != 16'd0));
assign fetch =
    ( sleep_instr & irq)
  | (~sleep_instr & ~jump);
assign stay =
  ~jump & ~fetch;

assign pc_next =
    ({8{jump }} & arg)
  | ({8{fetch}} & pc + 8'd1)
  | ({8{stay }} & pc);

dffr #(8) pc_dff (
  .dnxt(pc_next),
  .qout(pc),
  .clk(clk),
  .rst_n(rst_n)
);

wire load;
wire irq;
assign load = sleep_instr & ~sleep;
timer timer0 (
  .set(arg),
  .load(load),
  .irq(irq),
  .clk(clk),
  .rst_n(rst_n)
);

endmodule

processor_test.v
`timescale 1ms/1ns
module processor_test;

reg clk;
reg rst_n;

initial begin
    $dumpfile("processor_test.vcd");
    $dumpvars(0, processor_test);
end

always #(0.5)
  clk = ~clk;

initial begin
  clk <= 1'b0;
  rst_n <= 1'b0;
  #(2) rst_n <= 1'b1;
end

localparam op_wait    = 8'h01;
localparam op_fill    = 8'h02;
localparam op_release = 8'h03;
localparam op_forward = 8'h04;
localparam op_reverse = 8'h05;
localparam op_set     = 8'h11;
localparam op_dec     = 8'h12;
localparam op_jz      = 8'h21;

reg [31:0] instr = 32'd0;
wire [7:0] pc;
wire ctrl_fill;
wire ctrl_release;
wire ctrl_forward;
wire ctrl_reverse;

processor processor0 (
  .ena(1'b1),
  .instr(instr),
  .pc(pc),
  .ctrl_fill(ctrl_fill),
  .ctrl_release(ctrl_release),
  .ctrl_forward(ctrl_forward),
  .ctrl_reverse(ctrl_reverse),
  .clk(clk),
  .rst_n(rst_n)
);

initial begin
  #(2)
  instr = {16'h0020, 8'd0, op_fill};
  #(33)
  instr = {16'h0030, 8'd0, op_release};
  #(49)
  instr = {16'h0040, 8'd0, op_forward};
  #(65)
  instr = {16'h0050, 8'd0, op_reverse};
  #(81)
  instr = {16'h0060, 8'd0, op_wait};
  #(97)
  instr = {16'h00ab, 8'd0, op_set};
  #(16)
  instr = {16'h0000, 8'd0, op_dec};
  #(16)
  instr = {16'h00cd, 8'd0, op_jz};
  #(16)
  instr = {16'h0000, 8'd0, op_set};
  #(16)
  instr = {16'h00ef, 8'd0, op_jz};
  #(16)
  $finish;
end

endmodule

processor_test.vcd
$date
	Thu Mar  2 18:55:54 2023
$end
$version
	Icarus Verilog
$end
$timescale
	1ns
$end
$scope module processor_test $end
$var wire 8 ! pc [7:0] $end
$var wire 1 " ctrl_reverse $end
$var wire 1 # ctrl_release $end
$var wire 1 $ ctrl_forward $end
$var wire 1 % ctrl_fill $end
$var reg 1 & clk $end
$var reg 32 ' instr [31:0] $end
$var reg 1 ( rst_n $end
$scope module processor0 $end
$var wire 1 ) active_exit_ena $end
$var wire 1 & clk $end
$var wire 1 % ctrl_fill $end
$var wire 1 $ ctrl_forward $end
$var wire 1 # ctrl_release $end
$var wire 1 " ctrl_reverse $end
$var wire 1 * ena $end
$var wire 1 + fetch $end
$var wire 32 , instr [31:0] $end
$var wire 1 - jump $end
$var wire 1 . keep_state $end
$var wire 1 / load $end
$var wire 1 ( rst_n $end
$var wire 1 0 sleep_exit_ena $end
$var wire 1 1 sleep_next $end
$var wire 1 2 stay $end
$var wire 1 3 var_keep $end
$var wire 16 4 var_next [15:0] $end
$var wire 16 5 var [15:0] $end
$var wire 1 6 sleep_instr $end
$var wire 1 7 sleep $end
$var wire 8 8 reg_id [7:0] $end
$var wire 8 9 pc_next [7:0] $end
$var wire 8 : pc [7:0] $end
$var wire 8 ; opcode [7:0] $end
$var wire 1 < op_is_wait $end
$var wire 1 = op_is_set $end
$var wire 1 > op_is_reverse $end
$var wire 1 ? op_is_release $end
$var wire 1 @ op_is_jz $end
$var wire 1 A op_is_jnz $end
$var wire 1 B op_is_forward $end
$var wire 1 C op_is_fill $end
$var wire 1 D op_is_dec $end
$var wire 1 E irq $end
$var wire 16 F arg [15:0] $end
$scope module pc_dff $end
$var wire 1 & clk $end
$var wire 8 G dnxt [7:0] $end
$var wire 1 ( rst_n $end
$var wire 8 H qout [7:0] $end
$var reg 8 I qout_r [7:0] $end
$scope begin DFFR_PROC $end
$upscope $end
$upscope $end
$scope module sleep_dff $end
$var wire 1 & clk $end
$var wire 1 1 dnxt $end
$var wire 1 ( rst_n $end
$var wire 1 7 qout $end
$var reg 1 7 qout_r $end
$scope begin DFFR_PROC $end
$upscope $end
$upscope $end
$scope module timer0 $end
$var wire 1 & clk $end
$var wire 17 J cnt_next [16:0] $end
$var wire 17 K cnt_next_or_load [16:0] $end
$var wire 1 / load $end
$var wire 1 ( rst_n $end
$var wire 16 L set [15:0] $end
$var wire 1 M sign $end
$var wire 17 N set_ext [16:0] $end
$var wire 1 E irq $end
$var wire 17 O cnt [16:0] $end
$scope module timer_dff $end
$var wire 1 & clk $end
$var wire 17 P dnxt [16:0] $end
$var wire 1 ( rst_n $end
$var wire 17 Q qout [16:0] $end
$var reg 17 R qout_r [16:0] $end
$scope begin DFFRS_PROC $end
$upscope $end
$upscope $end
$upscope $end
$scope module var_dff $end
$var wire 1 & clk $end
$var wire 16 S dnxt [15:0] $end
$var wire 1 ( rst_n $end
$var wire 16 T qout [15:0] $end
$var reg 16 U qout_r [15:0] $end
$scope begin DFFR_PROC $end
$upscope $end
$upscope $end
$upscope $end
$upscope $end
$enddefinitions $end
#0
$dumpvars
b0 U
b0 T
b0 S
b11111111111111111 R
b11111111111111111 Q
b0 P
b11111111111111111 O
b0 N
1M
b0 L
b0 K
b11111111111111111 J
b0 I
b0 H
b0 G
b0 F
0E
0D
0C
0B
0A
0@
0?
0>
0=
0<
b0 ;
b0 :
b0 9
b0 8
07
16
b0 5
b0 4
13
12
11
00
1/
0.
0-
b0 ,
0+
1*
1)
0(
b0 '
0&
0%
0$
0#
0"
b0 !
$end
#500000
1&
#1000000
0&
#1500000
1&
#2000000
1(
b100000 K
b100000 P
1%
1C
b10 ;
b100000 N
b100000 F
b100000 L
0&
b1000000000000000000010 '
b1000000000000000000010 ,
#2500000
11
b11111 K
b11111 P
1.
b11111 J
0/
0)
0M
b100000 O
b100000 Q
b100000 R
17
1&
#3000000
0&
#3500000
b11110 K
b11110 P
b11110 J
b11111 O
b11111 Q
b11111 R
1&
#4000000
0&
#4500000
b11101 K
b11101 P
b11101 J
b11110 O
b11110 Q
b11110 R
1&
#5000000
0&
#5500000
b11100 K
b11100 P
b11100 J
b11101 O
b11101 Q
b11101 R
1&
#6000000
0&
#6500000
b11011 K
b11011 P
b11011 J
b11100 O
b11100 Q
b11100 R
1&
#7000000
0&
#7500000
b11010 K
b11010 P
b11010 J
b11011 O
b11011 Q
b11011 R
1&
#8000000
0&
#8500000
b11001 K
b11001 P
b11001 J
b11010 O
b11010 Q
b11010 R
1&
#9000000
0&
#9500000
b11000 K
b11000 P
b11000 J
b11001 O
b11001 Q
b11001 R
1&
#10000000
0&
#10500000
b10111 K
b10111 P
b10111 J
b11000 O
b11000 Q
b11000 R
1&
#11000000
0&
#11500000
b10110 K
b10110 P
b10110 J
b10111 O
b10111 Q
b10111 R
1&
#12000000
0&
#12500000
b10101 K
b10101 P
b10101 J
b10110 O
b10110 Q
b10110 R
1&
#13000000
0&
#13500000
b10100 K
b10100 P
b10100 J
b10101 O
b10101 Q
b10101 R
1&
#14000000
0&
#14500000
b10011 K
b10011 P
b10011 J
b10100 O
b10100 Q
b10100 R
1&
#15000000
0&
#15500000
b10010 K
b10010 P
b10010 J
b10011 O
b10011 Q
b10011 R
1&
#16000000
0&
#16500000
b10001 K
b10001 P
b10001 J
b10010 O
b10010 Q
b10010 R
1&
#17000000
0&
#17500000
b10000 K
b10000 P
b10000 J
b10001 O
b10001 Q
b10001 R
1&
#18000000
0&
#18500000
b1111 K
b1111 P
b1111 J
b10000 O
b10000 Q
b10000 R
1&
#19000000
0&
#19500000
b1110 K
b1110 P
b1110 J
b1111 O
b1111 Q
b1111 R
1&
#20000000
0&
#20500000
b1101 K
b1101 P
b1101 J
b1110 O
b1110 Q
b1110 R
1&
#21000000
0&
#21500000
b1100 K
b1100 P
b1100 J
b1101 O
b1101 Q
b1101 R
1&
#22000000
0&
#22500000
b1011 K
b1011 P
b1011 J
b1100 O
b1100 Q
b1100 R
1&
#23000000
0&
#23500000
b1010 K
b1010 P
b1010 J
b1011 O
b1011 Q
b1011 R
1&
#24000000
0&
#24500000
b1001 K
b1001 P
b1001 J
b1010 O
b1010 Q
b1010 R
1&
#25000000
0&
#25500000
b1000 K
b1000 P
b1000 J
b1001 O
b1001 Q
b1001 R
1&
#26000000
0&
#26500000
b111 K
b111 P
b111 J
b1000 O
b1000 Q
b1000 R
1&
#27000000
0&
#27500000
b110 K
b110 P
b110 J
b111 O
b111 Q
b111 R
1&
#28000000
0&
#28500000
b101 K
b101 P
b101 J
b110 O
b110 Q
b110 R
1&
#29000000
0&
#29500000
b100 K
b100 P
b100 J
b101 O
b101 Q
b101 R
1&
#30000000
0&
#30500000
b11 K
b11 P
b11 J
b100 O
b100 Q
b100 R
1&
#31000000
0&
#31500000
b10 K
b10 P
b10 J
b11 O
b11 Q
b11 R
1&
#32000000
0&
#32500000
b1 K
b1 P
b1 J
b10 O
b10 Q
b10 R
1&
#33000000
0&
#33500000
b0 K
b0 P
b0 J
b1 O
b1 Q
b1 R
1&
#34000000
0&
#34500000
b1 9
b1 G
01
b11111111111111111 K
b11111111111111111 P
02
0.
b11111111111111111 J
1+
0%
10
1E
b0 O
b0 Q
b0 R
1&
#35000000
1?
0C
b11 ;
b110000 N
b110000 F
b110000 L
0&
b1100000000000000000011 '
b1100000000000000000011 ,
#35500000
b110000 K
b110000 P
11
12
b1 9
b1 G
0+
1#
1/
1)
1M
00
0E
b11111111111111111 O
b11111111111111111 Q
b11111111111111111 R
b1 !
b1 :
b1 H
b1 I
07
1&
#36000000
0&
#36500000
11
b101111 K
b101111 P
1.
b101111 J
0/
0)
0M
b110000 O
b110000 Q
b110000 R
17
1&
#37000000
0&
#37500000
b101110 K
b101110 P
b101110 J
b101111 O
b101111 Q
b101111 R
1&
#38000000
0&
#38500000
b101101 K
b101101 P
b101101 J
b101110 O
b101110 Q
b101110 R
1&
#39000000
0&
#39500000
b101100 K
b101100 P
b101100 J
b101101 O
b101101 Q
b101101 R
1&
#40000000
0&
#40500000
b101011 K
b101011 P
b101011 J
b101100 O
b101100 Q
b101100 R
1&
#41000000
0&
#41500000
b101010 K
b101010 P
b101010 J
b101011 O
b101011 Q
b101011 R
1&
#42000000
0&
#42500000
b101001 K
b101001 P
b101001 J
b101010 O
b101010 Q
b101010 R
1&
#43000000
0&
#43500000
b101000 K
b101000 P
b101000 J
b101001 O
b101001 Q
b101001 R
1&
#44000000
0&
#44500000
b100111 K
b100111 P
b100111 J
b101000 O
b101000 Q
b101000 R
1&
#45000000
0&
#45500000
b100110 K
b100110 P
b100110 J
b100111 O
b100111 Q
b100111 R
1&
#46000000
0&
#46500000
b100101 K
b100101 P
b100101 J
b100110 O
b100110 Q
b100110 R
1&
#47000000
0&
#47500000
b100100 K
b100100 P
b100100 J
b100101 O
b100101 Q
b100101 R
1&
#48000000
0&
#48500000
b100011 K
b100011 P
b100011 J
b100100 O
b100100 Q
b100100 R
1&
#49000000
0&
#49500000
b100010 K
b100010 P
b100010 J
b100011 O
b100011 Q
b100011 R
1&
#50000000
0&
#50500000
b100001 K
b100001 P
b100001 J
b100010 O
b100010 Q
b100010 R
1&
#51000000
0&
#51500000
b100000 K
b100000 P
b100000 J
b100001 O
b100001 Q
b100001 R
1&
#52000000
0&
#52500000
b11111 K
b11111 P
b11111 J
b100000 O
b100000 Q
b100000 R
1&
#53000000
0&
#53500000
b11110 K
b11110 P
b11110 J
b11111 O
b11111 Q
b11111 R
1&
#54000000
0&
#54500000
b11101 K
b11101 P
b11101 J
b11110 O
b11110 Q
b11110 R
1&
#55000000
0&
#55500000
b11100 K
b11100 P
b11100 J
b11101 O
b11101 Q
b11101 R
1&
#56000000
0&
#56500000
b11011 K
b11011 P
b11011 J
b11100 O
b11100 Q
b11100 R
1&
#57000000
0&
#57500000
b11010 K
b11010 P
b11010 J
b11011 O
b11011 Q
b11011 R
1&
#58000000
0&
#58500000
b11001 K
b11001 P
b11001 J
b11010 O
b11010 Q
b11010 R
1&
#59000000
0&
#59500000
b11000 K
b11000 P
b11000 J
b11001 O
b11001 Q
b11001 R
1&
#60000000
0&
#60500000
b10111 K
b10111 P
b10111 J
b11000 O
b11000 Q
b11000 R
1&
#61000000
0&
#61500000
b10110 K
b10110 P
b10110 J
b10111 O
b10111 Q
b10111 R
1&
#62000000
0&
#62500000
b10101 K
b10101 P
b10101 J
b10110 O
b10110 Q
b10110 R
1&
#63000000
0&
#63500000
b10100 K
b10100 P
b10100 J
b10101 O
b10101 Q
b10101 R
1&
#64000000
0&
#64500000
b10011 K
b10011 P
b10011 J
b10100 O
b10100 Q
b10100 R
1&
#65000000
0&
#65500000
b10010 K
b10010 P
b10010 J
b10011 O
b10011 Q
b10011 R
1&
#66000000
0&
#66500000
b10001 K
b10001 P
b10001 J
b10010 O
b10010 Q
b10010 R
1&
#67000000
0&
#67500000
b10000 K
b10000 P
b10000 J
b10001 O
b10001 Q
b10001 R
1&
#68000000
0&
#68500000
b1111 K
b1111 P
b1111 J
b10000 O
b10000 Q
b10000 R
1&
#69000000
0&
#69500000
b1110 K
b1110 P
b1110 J
b1111 O
b1111 Q
b1111 R
1&
#70000000
0&
#70500000
b1101 K
b1101 P
b1101 J
b1110 O
b1110 Q
b1110 R
1&
#71000000
0&
#71500000
b1100 K
b1100 P
b1100 J
b1101 O
b1101 Q
b1101 R
1&
#72000000
0&
#72500000
b1011 K
b1011 P
b1011 J
b1100 O
b1100 Q
b1100 R
1&
#73000000
0&
#73500000
b1010 K
b1010 P
b1010 J
b1011 O
b1011 Q
b1011 R
1&
#74000000
0&
#74500000
b1001 K
b1001 P
b1001 J
b1010 O
b1010 Q
b1010 R
1&
#75000000
0&
#75500000
b1000 K
b1000 P
b1000 J
b1001 O
b1001 Q
b1001 R
1&
#76000000
0&
#76500000
b111 K
b111 P
b111 J
b1000 O
b1000 Q
b1000 R
1&
#77000000
0&
#77500000
b110 K
b110 P
b110 J
b111 O
b111 Q
b111 R
1&
#78000000
0&
#78500000
b101 K
b101 P
b101 J
b110 O
b110 Q
b110 R
1&
#79000000
0&
#79500000
b100 K
b100 P
b100 J
b101 O
b101 Q
b101 R
1&
#80000000
0&
#80500000
b11 K
b11 P
b11 J
b100 O
b100 Q
b100 R
1&
#81000000
0&
#81500000
b10 K
b10 P
b10 J
b11 O
b11 Q
b11 R
1&
#82000000
0&
#82500000
b1 K
b1 P
b1 J
b10 O
b10 Q
b10 R
1&
#83000000
0&
#83500000
b0 K
b0 P
b0 J
b1 O
b1 Q
b1 R
1&
#84000000
1$
0#
1B
0?
b100 ;
b1000000 N
b1000000 F
b1000000 L
0&
b10000000000000000000100 '
b10000000000000000000100 ,
#84500000
b10 9
b10 G
01
b11111111111111111 K
b11111111111111111 P
02
0.
b11111111111111111 J
1+
0$
10
1E
b0 O
b0 Q
b0 R
1&
#85000000
0&
#85500000
b1000000 K
b1000000 P
11
12
b10 9
b10 G
0+
1$
1/
1)
1M
00
0E
b11111111111111111 O
b11111111111111111 Q
b11111111111111111 R
b10 !
b10 :
b10 H
b10 I
07
1&
#86000000
0&
#86500000
11
b111111 K
b111111 P
1.
b111111 J
0/
0)
0M
b1000000 O
b1000000 Q
b1000000 R
17
1&
#87000000
0&
#87500000
b111110 K
b111110 P
b111110 J
b111111 O
b111111 Q
b111111 R
1&
#88000000
0&
#88500000
b111101 K
b111101 P
b111101 J
b111110 O
b111110 Q
b111110 R
1&
#89000000
0&
#89500000
b111100 K
b111100 P
b111100 J
b111101 O
b111101 Q
b111101 R
1&
#90000000
0&
#90500000
b111011 K
b111011 P
b111011 J
b111100 O
b111100 Q
b111100 R
1&
#91000000
0&
#91500000
b111010 K
b111010 P
b111010 J
b111011 O
b111011 Q
b111011 R
1&
#92000000
0&
#92500000
b111001 K
b111001 P
b111001 J
b111010 O
b111010 Q
b111010 R
1&
#93000000
0&
#93500000
b111000 K
b111000 P
b111000 J
b111001 O
b111001 Q
b111001 R
1&
#94000000
0&
#94500000
b110111 K
b110111 P
b110111 J
b111000 O
b111000 Q
b111000 R
1&
#95000000
0&
#95500000
b110110 K
b110110 P
b110110 J
b110111 O
b110111 Q
b110111 R
1&
#96000000
0&
#96500000
b110101 K
b110101 P
b110101 J
b110110 O
b110110 Q
b110110 R
1&
#97000000
0&
#97500000
b110100 K
b110100 P
b110100 J
b110101 O
b110101 Q
b110101 R
1&
#98000000
0&
#98500000
b110011 K
b110011 P
b110011 J
b110100 O
b110100 Q
b110100 R
1&
#99000000
0&
#99500000
b110010 K
b110010 P
b110010 J
b110011 O
b110011 Q
b110011 R
1&
#100000000
0&
#100500000
b110001 K
b110001 P
b110001 J
b110010 O
b110010 Q
b110010 R
1&
#101000000
0&
#101500000
b110000 K
b110000 P
b110000 J
b110001 O
b110001 Q
b110001 R
1&
#102000000
0&
#102500000
b101111 K
b101111 P
b101111 J
b110000 O
b110000 Q
b110000 R
1&
#103000000
0&
#103500000
b101110 K
b101110 P
b101110 J
b101111 O
b101111 Q
b101111 R
1&
#104000000
0&
#104500000
b101101 K
b101101 P
b101101 J
b101110 O
b101110 Q
b101110 R
1&
#105000000
0&
#105500000
b101100 K
b101100 P
b101100 J
b101101 O
b101101 Q
b101101 R
1&
#106000000
0&
#106500000
b101011 K
b101011 P
b101011 J
b101100 O
b101100 Q
b101100 R
1&
#107000000
0&
#107500000
b101010 K
b101010 P
b101010 J
b101011 O
b101011 Q
b101011 R
1&
#108000000
0&
#108500000
b101001 K
b101001 P
b101001 J
b101010 O
b101010 Q
b101010 R
1&
#109000000
0&
#109500000
b101000 K
b101000 P
b101000 J
b101001 O
b101001 Q
b101001 R
1&
#110000000
0&
#110500000
b100111 K
b100111 P
b100111 J
b101000 O
b101000 Q
b101000 R
1&
#111000000
0&
#111500000
b100110 K
b100110 P
b100110 J
b100111 O
b100111 Q
b100111 R
1&
#112000000
0&
#112500000
b100101 K
b100101 P
b100101 J
b100110 O
b100110 Q
b100110 R
1&
#113000000
0&
#113500000
b100100 K
b100100 P
b100100 J
b100101 O
b100101 Q
b100101 R
1&
#114000000
0&
#114500000
b100011 K
b100011 P
b100011 J
b100100 O
b100100 Q
b100100 R
1&
#115000000
0&
#115500000
b100010 K
b100010 P
b100010 J
b100011 O
b100011 Q
b100011 R
1&
#116000000
0&
#116500000
b100001 K
b100001 P
b100001 J
b100010 O
b100010 Q
b100010 R
1&
#117000000
0&
#117500000
b100000 K
b100000 P
b100000 J
b100001 O
b100001 Q
b100001 R
1&
#118000000
0&
#118500000
b11111 K
b11111 P
b11111 J
b100000 O
b100000 Q
b100000 R
1&
#119000000
0&
#119500000
b11110 K
b11110 P
b11110 J
b11111 O
b11111 Q
b11111 R
1&
#120000000
0&
#120500000
b11101 K
b11101 P
b11101 J
b11110 O
b11110 Q
b11110 R
1&
#121000000
0&
#121500000
b11100 K
b11100 P
b11100 J
b11101 O
b11101 Q
b11101 R
1&
#122000000
0&
#122500000
b11011 K
b11011 P
b11011 J
b11100 O
b11100 Q
b11100 R
1&
#123000000
0&
#123500000
b11010 K
b11010 P
b11010 J
b11011 O
b11011 Q
b11011 R
1&
#124000000
0&
#124500000
b11001 K
b11001 P
b11001 J
b11010 O
b11010 Q
b11010 R
1&
#125000000
0&
#125500000
b11000 K
b11000 P
b11000 J
b11001 O
b11001 Q
b11001 R
1&
#126000000
0&
#126500000
b10111 K
b10111 P
b10111 J
b11000 O
b11000 Q
b11000 R
1&
#127000000
0&
#127500000
b10110 K
b10110 P
b10110 J
b10111 O
b10111 Q
b10111 R
1&
#128000000
0&
#128500000
b10101 K
b10101 P
b10101 J
b10110 O
b10110 Q
b10110 R
1&
#129000000
0&
#129500000
b10100 K
b10100 P
b10100 J
b10101 O
b10101 Q
b10101 R
1&
#130000000
0&
#130500000
b10011 K
b10011 P
b10011 J
b10100 O
b10100 Q
b10100 R
1&
#131000000
0&
#131500000
b10010 K
b10010 P
b10010 J
b10011 O
b10011 Q
b10011 R
1&
#132000000
0&
#132500000
b10001 K
b10001 P
b10001 J
b10010 O
b10010 Q
b10010 R
1&
#133000000
0&
#133500000
b10000 K
b10000 P
b10000 J
b10001 O
b10001 Q
b10001 R
1&
#134000000
0&
#134500000
b1111 K
b1111 P
b1111 J
b10000 O
b10000 Q
b10000 R
1&
#135000000
0&
#135500000
b1110 K
b1110 P
b1110 J
b1111 O
b1111 Q
b1111 R
1&
#136000000
0&
#136500000
b1101 K
b1101 P
b1101 J
b1110 O
b1110 Q
b1110 R
1&
#137000000
0&
#137500000
b1100 K
b1100 P
b1100 J
b1101 O
b1101 Q
b1101 R
1&
#138000000
0&
#138500000
b1011 K
b1011 P
b1011 J
b1100 O
b1100 Q
b1100 R
1&
#139000000
0&
#139500000
b1010 K
b1010 P
b1010 J
b1011 O
b1011 Q
b1011 R
1&
#140000000
0&
#140500000
b1001 K
b1001 P
b1001 J
b1010 O
b1010 Q
b1010 R
1&
#141000000
0&
#141500000
b1000 K
b1000 P
b1000 J
b1001 O
b1001 Q
b1001 R
1&
#142000000
0&
#142500000
b111 K
b111 P
b111 J
b1000 O
b1000 Q
b1000 R
1&
#143000000
0&
#143500000
b110 K
b110 P
b110 J
b111 O
b111 Q
b111 R
1&
#144000000
0&
#144500000
b101 K
b101 P
b101 J
b110 O
b110 Q
b110 R
1&
#145000000
0&
#145500000
b100 K
b100 P
b100 J
b101 O
b101 Q
b101 R
1&
#146000000
0&
#146500000
b11 K
b11 P
b11 J
b100 O
b100 Q
b100 R
1&
#147000000
0&
#147500000
b10 K
b10 P
b10 J
b11 O
b11 Q
b11 R
1&
#148000000
0&
#148500000
b1 K
b1 P
b1 J
b10 O
b10 Q
b10 R
1&
#149000000
1"
0$
1>
0B
b101 ;
b1010000 N
b1010000 F
b1010000 L
0&
b10100000000000000000101 '
b10100000000000000000101 ,
#149500000
b0 K
b0 P
b0 J
b1 O
b1 Q
b1 R
1&
#150000000
0&
#150500000
b11 9
b11 G
01
b11111111111111111 K
b11111111111111111 P
02
0.
b11111111111111111 J
1+
0"
10
1E
b0 O
b0 Q
b0 R
1&
#151000000
0&
#151500000
b1010000 K
b1010000 P
11
12
b11 9
b11 G
0+
1"
1/
1)
1M
00
0E
b11111111111111111 O
b11111111111111111 Q
b11111111111111111 R
b11 !
b11 :
b11 H
b11 I
07
1&
#152000000
0&
#152500000
11
b1001111 K
b1001111 P
1.
b1001111 J
0/
0)
0M
b1010000 O
b1010000 Q
b1010000 R
17
1&
#153000000
0&
#153500000
b1001110 K
b1001110 P
b1001110 J
b1001111 O
b1001111 Q
b1001111 R
1&
#154000000
0&
#154500000
b1001101 K
b1001101 P
b1001101 J
b1001110 O
b1001110 Q
b1001110 R
1&
#155000000
0&
#155500000
b1001100 K
b1001100 P
b1001100 J
b1001101 O
b1001101 Q
b1001101 R
1&
#156000000
0&
#156500000
b1001011 K
b1001011 P
b1001011 J
b1001100 O
b1001100 Q
b1001100 R
1&
#157000000
0&
#157500000
b1001010 K
b1001010 P
b1001010 J
b1001011 O
b1001011 Q
b1001011 R
1&
#158000000
0&
#158500000
b1001001 K
b1001001 P
b1001001 J
b1001010 O
b1001010 Q
b1001010 R
1&
#159000000
0&
