dff.v
// ===========================================================================
//
// Description:
//  Verilog module sirv_gnrl DFF with Load-enable and Reset
//  Default reset value is 1
//
// ===========================================================================
module dfflrs # (
  parameter DW = 32
) (

  input               lden, 
  input      [DW-1:0] dnxt,
  output     [DW-1:0] qout,

  input               clk,
  input               rst_n
);

reg [DW-1:0] qout_r;

always @(posedge clk or negedge rst_n)
begin : DFFLRS_PROC
  if (rst_n == 1'b0)
    qout_r <= {DW{1'b1}};
  else if (lden == 1'b1)
    qout_r <= dnxt;
end

assign qout = qout_r;


endmodule
// ===========================================================================
//
// Description:
//  Verilog module sirv_gnrl DFF with Load-enable and Reset
//  Default reset value is 0
//
// ===========================================================================

module dfflr # (
  parameter DW = 32
) (

  input               lden, 
  input      [DW-1:0] dnxt,
  output     [DW-1:0] qout,

  input               clk,
  input               rst_n
);

reg [DW-1:0] qout_r;

always @(posedge clk or negedge rst_n)
begin : DFFLR_PROC
  if (rst_n == 1'b0)
    qout_r <= {DW{1'b0}};
  else if (lden == 1'b1)
    qout_r <= #1 dnxt;
end

assign qout = qout_r;


endmodule
// ===========================================================================
//
// Description:
//  Verilog module sirv_gnrl DFF with Load-enable, no reset 
//
// ===========================================================================

module dffl # (
  parameter DW = 32
) (

  input               lden, 
  input      [DW-1:0] dnxt,
  output     [DW-1:0] qout,

  input               clk 
);

reg [DW-1:0] qout_r;

always @(posedge clk)
begin : DFFL_PROC
  if (lden == 1'b1)
    qout_r <= #1 dnxt;
end

assign qout = qout_r;


endmodule
// ===========================================================================
//
// Description:
//  Verilog module sirv_gnrl DFF with Reset, no load-enable
//  Default reset value is 1
//
// ===========================================================================

module dffrs # (
  parameter DW = 32
) (

  input      [DW-1:0] dnxt,
  output     [DW-1:0] qout,

  input               clk,
  input               rst_n
);

reg [DW-1:0] qout_r;

always @(posedge clk or negedge rst_n)
begin : DFFRS_PROC
  if (rst_n == 1'b0)
    qout_r <= {DW{1'b1}};
  else                  
    qout_r <= dnxt;
end

assign qout = qout_r;

endmodule
// ===========================================================================
//
// Description:
//  Verilog module sirv_gnrl DFF with Reset, no load-enable
//  Default reset value is 0
//
// ===========================================================================

module dffr # (
  parameter DW = 32
) (

  input      [DW-1:0] dnxt,
  output     [DW-1:0] qout,

  input               clk,
  input               rst_n
);

reg [DW-1:0] qout_r;

always @(posedge clk or negedge rst_n)
begin : DFFR_PROC
  if (rst_n == 1'b0)
    qout_r <= {DW{1'b0}};
  else                  
    qout_r <= dnxt;
end

assign qout = qout_r;

endmodule
// ===========================================================================
//
// Description:
//  Verilog module for general latch 
//
// ===========================================================================

module sirv_gnrl_ltch # (
  parameter DW = 32
) (

  //input               test_mode,
  input               lden, 
  input      [DW-1:0] dnxt,
  output     [DW-1:0] qout
);

reg [DW-1:0] qout_r;

always @ (*) 
begin : LTCH_PROC
  if (lden == 1'b1)
    qout_r <= dnxt;
end

//assign qout = test_mode ? dnxt : qout_r;
assign qout = qout_r;


endmodule

timer.v
module timer # (
  parameter WIDTH = 16
) (
  input [WIDTH-1:0] set,
  input       load,
  output      irq,

  input clk,
  input rst_n
);

wire [WIDTH:0] cnt;
wire [WIDTH:0] cnt_next;
wire [WIDTH:0] cnt_next_or_load;
wire sign = cnt[WIDTH];

assign irq = cnt == 17'd0;

wire [WIDTH:0] set_ext;
assign set_ext = {1'b0, set};

assign cnt_next =
    ({(WIDTH+1){~sign}} & (cnt - 17'd1))
  | ({(WIDTH+1){ sign}} & 17'h1ffff);

assign cnt_next_or_load =
    ({(WIDTH+1){ load}} & set_ext)
  | ({(WIDTH+1){~load}} & cnt_next);

dffrs #(WIDTH+1) timer_dff (
  .dnxt(cnt_next_or_load),
  .qout(cnt),
  .clk(clk),
  .rst_n(rst_n)
);

endmodule

processor.v
module processor # (
  parameter OPCODE_WIDTH = 8,
  parameter REG_WIDTH = 8,
  parameter IMME_WIDTH = 16,
  parameter INSTRS_WIDTH = 32,
  parameter ADDR_WIDTH = 8,
  parameter REG_NUM = 2
) (
  input                     ena,
  input  [INSTRS_WIDTH-1:0] instr,
  output   [ADDR_WIDTH-1:0] pc,

  output ctrl_fill,
  output ctrl_release,
  output ctrl_forward,
  output ctrl_reverse,

  input clk,
  input rst_n
);

localparam op_wait    = 8'h01;
localparam op_fill    = 8'h02;
localparam op_release = 8'h03;
localparam op_forward = 8'h04;
localparam op_reverse = 8'h05;
localparam op_set     = 8'h11;
localparam op_dec     = 8'h12;
localparam op_jz      = 8'h21;
localparam op_jnz     = 8'h22;

wire op_is_wait;
wire op_is_fill;
wire op_is_release;
wire op_is_forward;
wire op_is_reverse;
wire op_is_set;
wire op_is_dec;
wire op_is_jz;
wire op_is_jnz;

assign op_is_wait    = opcode == op_wait;
assign op_is_fill    = opcode == op_fill;
assign op_is_release = opcode == op_release;
assign op_is_forward = opcode == op_forward;
assign op_is_reverse = opcode == op_reverse;
assign op_is_set     = opcode == op_set;
assign op_is_dec     = opcode == op_dec;
assign op_is_jz      = opcode == op_jz;
assign op_is_jnz     = opcode == op_jnz;


wire [7:0] opcode;
wire [7:0] reg_id;
wire [15:0] arg;

assign opcode = instr[7:0];
assign reg_id = instr[15:8];
assign arg = instr[31:16];

wire sleep;
wire sleep_next;
wire sleep_instr;
wire sleep_exit_ena;
wire active_exit_ena;
wire keep_state;

assign sleep_instr =
  opcode[7:4] == 4'd0;
assign active_exit_ena =
  (~sleep) & sleep_instr;
assign sleep_exit_ena =
  sleep & irq;
assign keep_state =
  ~active_exit_ena & ~sleep_exit_ena;

assign sleep_next =
    (active_exit_ena & 1'b1)
  | (sleep_exit_ena  & 1'b0)
  | (keep_state      & sleep);

dffr #(1) sleep_dff (
  .dnxt(sleep_next),
  .qout(sleep),
  .clk(clk),
  .rst_n(rst_n)
);

assign ctrl_fill    = ~irq & op_is_fill;
assign ctrl_release = ~irq & op_is_release;
assign ctrl_forward = ~irq & op_is_forward;
assign ctrl_reverse = ~irq & op_is_reverse;

wire [15:0] var [0:REG_NUM-1];
wire [15:0] var_next [0:REG_NUM-1];
wire var_set [0:REG_NUM-1];
wire var_dec [0:REG_NUM-1];
wire var_keep [0:REG_NUM-1];

genvar i;
generate
  for (i = 0; i < REG_NUM; i = i + 1) begin : var_loop
    assign var_set[i] = (reg_id == i) & op_is_set;
    assign var_dec[i] = (reg_id == i) & op_is_dec;
    assign var_keep[i] = ~var_set[i] & ~var_dec[i];
    assign var_next[i] =
        ({16{ var_set[i]}} & arg)
      | ({16{ var_dec[i]}} & (var[i] - 16'd1))
      | ({16{var_keep[i]}} & var[i]);
    dffr #(16) var_dff (
      .dnxt(var_next[i]),
      .qout(var[i]),
      .clk(clk),
      .rst_n(rst_n)
    );
  end
endgenerate

wire [7:0] pc;
wire [7:0] pc_next;

wire fetch;
wire jump;
wire stay;

assign jump =
    (op_is_jz  & (var[reg_id] == 16'd0))
  | (op_is_jnz & (var[reg_id] != 16'd0));
assign fetch =
    ( sleep_instr & irq)
  | (~sleep_instr & ~jump);
assign stay =
  ~jump & ~fetch;

assign pc_next =
    ({8{jump }} & arg)
  | ({8{fetch}} & pc + 8'd1)
  | ({8{stay }} & pc);

dffr #(8) pc_dff (
  .dnxt(pc_next),
  .qout(pc),
  .clk(clk),
  .rst_n(rst_n)
);

wire load;
wire irq;
assign load = sleep_instr & ~sleep;
timer timer0 (
  .set(arg),
  .load(load),
  .irq(irq),
  .clk(clk),
  .rst_n(rst_n)
);

endmodule

processor_test.v
`timescale 1ms/1ns
module processor_test;

reg clk;
reg rst_n;

initial begin
    $dumpfile("processor_test.vcd");
    $dumpvars(0, processor_test);
end

always #(0.5)
  clk = ~clk;

initial begin
  clk <= 1'b0;
  rst_n <= 1'b0;
  #(2) rst_n <= 1'b1;
end

localparam op_wait    = 8'h01;
localparam op_fill    = 8'h02;
localparam op_release = 8'h03;
localparam op_forward = 8'h04;
localparam op_reverse = 8'h05;
localparam op_set     = 8'h11;
localparam op_dec     = 8'h12;
localparam op_jz      = 8'h21;
localparam op_jnz     = 8'h22;

reg [31:0] instr = 32'd0;
wire [7:0] pc;
wire ctrl_fill;
wire ctrl_release;
wire ctrl_forward;
wire ctrl_reverse;

processor processor0 (
  .ena(1'b1),
  .instr(instr),
  .pc(pc),
  .ctrl_fill(ctrl_fill),
  .ctrl_release(ctrl_release),
  .ctrl_forward(ctrl_forward),
  .ctrl_reverse(ctrl_reverse),
  .clk(clk),
  .rst_n(rst_n)
);

initial begin
  #(2)
  instr = {16'h0020, 8'd0, op_fill};
  #(33)
  instr = {16'h0030, 8'd0, op_release};
  #(49)
  instr = {16'h0040, 8'd0, op_forward};
  #(65)
  instr = {16'h0050, 8'd0, op_reverse};
  #(81)
  instr = {16'h0060, 8'd0, op_wait};
  #(97)
  instr = {16'h00ab, 8'd0, op_set};
  #(16)
  instr = {16'h0000, 8'd0, op_dec};
  #(16)
  instr = {16'h00cd, 8'd0, op_jz};
  #(16)
  instr = {16'h0000, 8'd0, op_set};
  #(16)
  instr = {16'h00ef, 8'd0, op_jz};
  #(16)
  instr = {16'h00ea, 8'd1, op_set};
  #(16)
  instr = {16'h00fe, 8'd1, op_jz};
  #(16)
  instr = {16'h00fe, 8'd1, op_jnz};
  #(16)
  $finish;
end

endmodule

processor_test.vcd
$date
	Thu Mar  2 19:54:18 2023
$end
$version
	Icarus Verilog
$end
$timescale
	1ns
$end
$scope module processor_test $end
$var wire 8 ! pc [7:0] $end
$var wire 1 " ctrl_reverse $end
$var wire 1 # ctrl_release $end
$var wire 1 $ ctrl_forward $end
$var wire 1 % ctrl_fill $end
$var reg 1 & clk $end
$var reg 32 ' instr [31:0] $end
$var reg 1 ( rst_n $end
$scope module processor0 $end
$var wire 1 ) active_exit_ena $end
$var wire 1 & clk $end
$var wire 1 % ctrl_fill $end
$var wire 1 $ ctrl_forward $end
$var wire 1 # ctrl_release $end
$var wire 1 " ctrl_reverse $end
$var wire 1 * ena $end
$var wire 1 + fetch $end
$var wire 32 , instr [31:0] $end
$var wire 1 - jump $end
$var wire 1 . keep_state $end
$var wire 1 / load $end
$var wire 1 ( rst_n $end
$var wire 1 0 sleep_exit_ena $end
$var wire 1 1 sleep_next $end
$var wire 1 2 stay $end
$var wire 1 3 sleep_instr $end
$var wire 1 4 sleep $end
$var wire 8 5 reg_id [7:0] $end
$var wire 8 6 pc_next [7:0] $end
$var wire 8 7 pc [7:0] $end
$var wire 8 8 opcode [7:0] $end
$var wire 1 9 op_is_wait $end
$var wire 1 : op_is_set $end
$var wire 1 ; op_is_reverse $end
$var wire 1 < op_is_release $end
$var wire 1 = op_is_jz $end
$var wire 1 > op_is_jnz $end
$var wire 1 ? op_is_forward $end
$var wire 1 @ op_is_fill $end
$var wire 1 A op_is_dec $end
$var wire 1 B irq $end
$var wire 16 C arg [15:0] $end
$scope begin var_loop[0] $end
$scope module var_dff $end
$var wire 1 & clk $end
$var wire 16 D dnxt [15:0] $end
$var wire 1 ( rst_n $end
$var wire 16 E qout [15:0] $end
$var reg 16 F qout_r [15:0] $end
$scope begin DFFR_PROC $end
$upscope $end
$upscope $end
$upscope $end
$scope begin var_loop[1] $end
$scope module var_dff $end
$var wire 1 & clk $end
$var wire 16 G dnxt [15:0] $end
$var wire 1 ( rst_n $end
$var wire 16 H qout [15:0] $end
$var reg 16 I qout_r [15:0] $end
$scope begin DFFR_PROC $end
$upscope $end
$upscope $end
$upscope $end
$scope module pc_dff $end
$var wire 1 & clk $end
$var wire 8 J dnxt [7:0] $end
$var wire 1 ( rst_n $end
$var wire 8 K qout [7:0] $end
$var reg 8 L qout_r [7:0] $end
$scope begin DFFR_PROC $end
$upscope $end
$upscope $end
$scope module sleep_dff $end
$var wire 1 & clk $end
$var wire 1 1 dnxt $end
$var wire 1 ( rst_n $end
$var wire 1 4 qout $end
$var reg 1 4 qout_r $end
$scope begin DFFR_PROC $end
$upscope $end
$upscope $end
$scope module timer0 $end
$var wire 1 & clk $end
$var wire 17 M cnt_next [16:0] $end
$var wire 17 N cnt_next_or_load [16:0] $end
$var wire 1 / load $end
$var wire 1 ( rst_n $end
$var wire 16 O set [15:0] $end
$var wire 1 P sign $end
$var wire 17 Q set_ext [16:0] $end
$var wire 1 B irq $end
$var wire 17 R cnt [16:0] $end
$scope module timer_dff $end
$var wire 1 & clk $end
$var wire 17 S dnxt [16:0] $end
$var wire 1 ( rst_n $end
$var wire 17 T qout [16:0] $end
$var reg 17 U qout_r [16:0] $end
$scope begin DFFRS_PROC $end
$upscope $end
$upscope $end
$upscope $end
$upscope $end
$upscope $end
$enddefinitions $end
#0
$dumpvars
b11111111111111111 U
b11111111111111111 T
b0 S
b11111111111111111 R
b0 Q
1P
b0 O
b0 N
b11111111111111111 M
b0 L
b0 K
b0 J
b0 I
b0 H
b0 G
b0 F
b0 E
b0 D
b0 C
0B
0A
0@
0?
0>
0=
0<
0;
0:
09
b0 8
b0 7
b0 6
b0 5
04
13
12
11
00
1/
0.
0-
b0 ,
0+
1*
1)
0(
b0 '
0&
0%
0$
0#
0"
b0 !
$end
#500000
1&
#1000000
0&
#1500000
1&
#2000000
1(
b100000 N
b100000 S
1%
1@
b10 8
b100000 Q
b100000 C
b100000 O
0&
b1000000000000000000010 '
b1000000000000000000010 ,
#2500000
11
b11111 N
b11111 S
1.
b11111 M
0/
0)
0P
b100000 R
b100000 T
b100000 U
14
1&
#3000000
0&
#3500000
b11110 N
b11110 S
b11110 M
b11111 R
b11111 T
b11111 U
1&
#4000000
0&
#4500000
b11101 N
b11101 S
b11101 M
b11110 R
b11110 T
b11110 U
1&
#5000000
0&
#5500000
b11100 N
b11100 S
b11100 M
b11101 R
b11101 T
b11101 U
1&
#6000000
0&
#6500000
b11011 N
b11011 S
b11011 M
b11100 R
b11100 T
b11100 U
1&
#7000000
0&
#7500000
b11010 N
b11010 S
b11010 M
b11011 R
b11011 T
b11011 U
1&
#8000000
0&
#8500000
b11001 N
b11001 S
b11001 M
b11010 R
b11010 T
b11010 U
1&
#9000000
0&
#9500000
b11000 N
b11000 S
b11000 M
b11001 R
b11001 T
b11001 U
1&
#10000000
0&
#10500000
b10111 N
b10111 S
b10111 M
b11000 R
b11000 T
b11000 U
1&
#11000000
0&
#11500000
b10110 N
b10110 S
b10110 M
b10111 R
b10111 T
b10111 U
1&
#12000000
0&
#12500000
b10101 N
b10101 S
b10101 M
b10110 R
b10110 T
b10110 U
1&
#13000000
0&
#13500000
b10100 N
b10100 S
b10100 M
b10101 R
b10101 T
b10101 U
1&
#14000000
0&
#14500000
b10011 N
b10011 S
b10011 M
b10100 R
b10100 T
b10100 U
1&
#15000000
0&
#15500000
b10010 N
b10010 S
b10010 M
b10011 R
b10011 T
b10011 U
1&
#16000000
0&
#16500000
b10001 N
b10001 S
b10001 M
b10010 R
b10010 T
b10010 U
1&
#17000000
0&
#17500000
b10000 N
b10000 S
b10000 M
b10001 R
b10001 T
b10001 U
1&
#18000000
0&
#18500000
b1111 N
b1111 S
b1111 M
b10000 R
b10000 T
b10000 U
1&
#19000000
0&
#19500000
b1110 N
b1110 S
b1110 M
b1111 R
b1111 T
b1111 U
1&
#20000000
0&
#20500000
b1101 N
b1101 S
b1101 M
b1110 R
b1110 T
b1110 U
1&
#21000000
0&
#21500000
b1100 N
b1100 S
b1100 M
b1101 R
b1101 T
b1101 U
1&
#22000000
0&
#22500000
b1011 N
b1011 S
b1011 M
b1100 R
b1100 T
b1100 U
1&
#23000000
0&
#23500000
b1010 N
b1010 S
b1010 M
b1011 R
b1011 T
b1011 U
1&
#24000000
0&
#24500000
b1001 N
b1001 S
b1001 M
b1010 R
b1010 T
b1010 U
1&
#25000000
0&
#25500000
b1000 N
b1000 S
b1000 M
b1001 R
b1001 T
b1001 U
1&
#26000000
0&
#26500000
b111 N
b111 S
b111 M
b1000 R
b1000 T
b1000 U
1&
#27000000
0&
#27500000
b110 N
b110 S
b110 M
b111 R
b111 T
b111 U
1&
#28000000
0&
#28500000
b101 N
b101 S
b101 M
b110 R
b110 T
b110 U
1&
#29000000
0&
#29500000
b100 N
b100 S
b100 M
b101 R
b101 T
b101 U
1&
#30000000
0&
#30500000
b11 N
b11 S
b11 M
b100 R
b100 T
b100 U
1&
#31000000
0&
#31500000
b10 N
b10 S
b10 M
b11 R
b11 T
b11 U
1&
#32000000
0&
#32500000
b1 N
b1 S
b1 M
b10 R
b10 T
b10 U
1&
#33000000
0&
#33500000
b0 N
b0 S
b0 M
b1 R
b1 T
b1 U
1&
#34000000
0&
#34500000
b1 6
b1 J
01
b11111111111111111 N
b11111111111111111 S
02
0.
b11111111111111111 M
1+
0%
10
1B
b0 R
b0 T
b0 U
1&
#35000000
1<
0@
b11 8
b110000 Q
b110000 C
b110000 O
0&
b1100000000000000000011 '
b1100000000000000000011 ,
#35500000
b110000 N
b110000 S
11
12
b1 6
b1 J
0+
1#
1/
1)
1P
00
0B
b11111111111111111 R
b11111111111111111 T
b11111111111111111 U
b1 !
b1 7
b1 K
b1 L
04
1&
#36000000
0&
#36500000
11
b101111 N
b101111 S
1.
b101111 M
0/
0)
0P
b110000 R
b110000 T
b110000 U
14
1&
#37000000
0&
#37500000
b101110 N
b101110 S
b101110 M
b101111 R
b101111 T
b101111 U
1&
#38000000
0&
#38500000
b101101 N
b101101 S
b101101 M
b101110 R
b101110 T
b101110 U
1&
#39000000
0&
#39500000
b101100 N
b101100 S
b101100 M
b101101 R
b101101 T
b101101 U
1&
#40000000
0&
#40500000
b101011 N
b101011 S
b101011 M
b101100 R
b101100 T
b101100 U
1&
#41000000
0&
#41500000
b101010 N
b101010 S
b101010 M
b101011 R
b101011 T
b101011 U
1&
#42000000
0&
#42500000
b101001 N
b101001 S
b101001 M
b101010 R
b101010 T
b101010 U
1&
#43000000
0&
#43500000
b101000 N
b101000 S
b101000 M
b101001 R
b101001 T
b101001 U
1&
#44000000
0&
#44500000
b100111 N
b100111 S
b100111 M
b101000 R
b101000 T
b101000 U
1&
#45000000
0&
#45500000
b100110 N
b100110 S
b100110 M
b100111 R
b100111 T
b100111 U
1&
#46000000
0&
#46500000
b100101 N
b100101 S
b100101 M
b100110 R
b100110 T
b100110 U
1&
#47000000
0&
#47500000
b100100 N
b100100 S
b100100 M
b100101 R
b100101 T
b100101 U
1&
#48000000
0&
#48500000
b100011 N
b100011 S
b100011 M
b100100 R
b100100 T
b100100 U
1&
#49000000
0&
#49500000
b100010 N
b100010 S
b100010 M
b100011 R
b100011 T
b100011 U
1&
#50000000
0&
#50500000
b100001 N
b100001 S
b100001 M
b100010 R
b100010 T
b100010 U
1&
#51000000
0&
#51500000
b100000 N
b100000 S
b100000 M
b100001 R
b100001 T
b100001 U
1&
#52000000
0&
#52500000
b11111 N
b11111 S
b11111 M
b100000 R
b100000 T
b100000 U
1&
#53000000
0&
#53500000
b11110 N
b11110 S
b11110 M
b11111 R
b11111 T
b11111 U
1&
#54000000
0&
#54500000
b11101 N
b11101 S
b11101 M
b11110 R
b11110 T
b11110 U
1&
#55000000
0&
#55500000
b11100 N
b11100 S
b11100 M
b11101 R
b11101 T
b11101 U
1&
#56000000
0&
#56500000
b11011 N
b11011 S
b11011 M
b11100 R
b11100 T
b11100 U
1&
#57000000
0&
#57500000
b11010 N
b11010 S
b11010 M
b11011 R
b11011 T
b11011 U
1&
#58000000
0&
#58500000
b11001 N
b11001 S
b11001 M
b11010 R
b11010 T
b11010 U
1&
#59000000
0&
#59500000
b11000 N
b11000 S
b11000 M
b11001 R
b11001 T
b11001 U
1&
#60000000
0&
#60500000
b10111 N
b10111 S
b10111 M
b11000 R
b11000 T
b11000 U
1&
#61000000
0&
#61500000
b10110 N
b10110 S
b10110 M
b10111 R
b10111 T
b10111 U
1&
#62000000
0&
#62500000
b10101 N
b10101 S
b10101 M
b10110 R
b10110 T
b10110 U
1&
#63000000
0&
#63500000
b10100 N
b10100 S
b10100 M
b10101 R
b10101 T
b10101 U
1&
#64000000
0&
#64500000
b10011 N
b10011 S
b10011 M
b10100 R
b10100 T
b10100 U
1&
#65000000
0&
#65500000
b10010 N
b10010 S
b10010 M
b10011 R
b10011 T
b10011 U
1&
#66000000
0&
#66500000
b10001 N
b10001 S
b10001 M
b10010 R
b10010 T
b10010 U
1&
#67000000
0&
#67500000
b10000 N
b10000 S
b10000 M
b10001 R
b10001 T
b10001 U
1&
#68000000
0&
#68500000
b1111 N
b1111 S
b1111 M
b10000 R
b10000 T
b10000 U
1&
#69000000
0&
#69500000
b1110 N
b1110 S
b1110 M
b1111 R
b1111 T
b1111 U
1&
#70000000
0&
#70500000
b1101 N
b1101 S
b1101 M
b1110 R
b1110 T
b1110 U
1&
#71000000
0&
#71500000
b1100 N
b1100 S
b1100 M
b1101 R
b1101 T
b1101 U
1&
#72000000
0&
#72500000
b1011 N
b1011 S
b1011 M
b1100 R
b1100 T
b1100 U
1&
#73000000
0&
#73500000
b1010 N
b1010 S
b1010 M
b1011 R
b1011 T
b1011 U
1&
#74000000
0&
#74500000
b1001 N
b1001 S
b1001 M
b1010 R
b1010 T
b1010 U
1&
#75000000
0&
#75500000
b1000 N
b1000 S
b1000 M
b1001 R
b1001 T
b1001 U
1&
#76000000
0&
#76500000
b111 N
b111 S
b111 M
b1000 R
b1000 T
b1000 U
1&
#77000000
0&
#77500000
b110 N
b110 S
b110 M
b111 R
b111 T
b111 U
1&
#78000000
0&
#78500000
b101 N
b101 S
b101 M
b110 R
b110 T
b110 U
1&
#79000000
0&
#79500000
b100 N
b100 S
b100 M
b101 R
b101 T
b101 U
1&
#80000000
0&
#80500000
b11 N
b11 S
b11 M
b100 R
b100 T
b100 U
1&
#81000000
0&
#81500000
b10 N
b10 S
b10 M
b11 R
b11 T
b11 U
1&
#82000000
0&
#82500000
b1 N
b1 S
b1 M
b10 R
b10 T
b10 U
1&
#83000000
0&
#83500000
b0 N
b0 S
b0 M
b1 R
b1 T
b1 U
1&
#84000000
1$
0#
1?
0<
b100 8
b1000000 Q
b1000000 C
b1000000 O
0&
b10000000000000000000100 '
b10000000000000000000100 ,
#84500000
b10 6
b10 J
01
b11111111111111111 N
b11111111111111111 S
02
0.
b11111111111111111 M
1+
0$
10
1B
b0 R
b0 T
b0 U
1&
#85000000
0&
#85500000
b1000000 N
b1000000 S
11
12
b10 6
b10 J
0+
1$
1/
1)
1P
00
0B
b11111111111111111 R
b11111111111111111 T
b11111111111111111 U
b10 !
b10 7
b10 K
b10 L
04
1&
#86000000
0&
#86500000
11
b111111 N
b111111 S
1.
b111111 M
0/
0)
0P
b1000000 R
b1000000 T
b1000000 U
14
1&
#87000000
0&
#87500000
b111110 N
b111110 S
b111110 M
b111111 R
b111111 T
b111111 U
1&
#88000000
0&
#88500000
b111101 N
b111101 S
b111101 M
b111110 R
b111110 T
b111110 U
1&
#89000000
0&
#89500000
b111100 N
b111100 S
b111100 M
b111101 R
b111101 T
b111101 U
1&
#90000000
0&
#90500000
b111011 N
b111011 S
b111011 M
b111100 R
b111100 T
b111100 U
1&
#91000000
0&
#91500000
b111010 N
b111010 S
b111010 M
b111011 R
b111011 T
b111011 U
1&
#92000000
0&
#92500000
b111001 N
b111001 S
b111001 M
b111010 R
b111010 T
b111010 U
1&
#93000000
0&
#93500000
b111000 N
b111000 S
b111000 M
b111001 R
b111001 T
b111001 U
1&
#94000000
0&
#94500000
b110111 N
b110111 S
b110111 M
b111000 R
b111000 T
b111000 U
1&
#95000000
0&
#95500000
b110110 N
b110110 S
b110110 M
b110111 R
b110111 T
b110111 U
1&
#96000000
0&
#96500000
b110101 N
b110101 S
b110101 M
b110110 R
b110110 T
b110110 U
1&
#97000000
0&
#97500000
b110100 N
b110100 S
b110100 M
b110101 R
b110101 T
b110101 U
1&
#98000000
0&
#98500000
b110011 N
b110011 S
b110011 M
b110100 R
b110100 T
b110100 U
1&
#99000000
0&
#99500000
b110010 N
b110010 S
b110010 M
b110011 R
b110011 T
b110011 U
1&
#100000000
0&
#100500000
b110001 N
b110001 S
b110001 M
b110010 R
b110010 T
b110010 U
1&
#101000000
0&
#101500000
b110000 N
b110000 S
b110000 M
b110001 R
b110001 T
b110001 U
1&
#102000000
0&
#102500000
b101111 N
b101111 S
b101111 M
b110000 R
b110000 T
b110000 U
1&
#103000000
0&
#103500000
b101110 N
b101110 S
b101110 M
b101111 R
b101111 T
b101111 U
1&
#104000000
0&
#104500000
b101101 N
b101101 S
b101101 M
b101110 R
b101110 T
b101110 U
1&
#105000000
0&
#105500000
b101100 N
b101100 S
b101100 M
b101101 R
b101101 T
b101101 U
1&
#106000000
0&
#106500000
b101011 N
b101011 S
b101011 M
b101100 R
b101100 T
b101100 U
1&
#107000000
0&
#107500000
b101010 N
b101010 S
b101010 M
b101011 R
b101011 T
b101011 U
1&
#108000000
0&
#108500000
b101001 N
b101001 S
b101001 M
b101010 R
b101010 T
b101010 U
1&
#109000000
0&
#109500000
b101000 N
b101000 S
b101000 M
b101001 R
b101001 T
b101001 U
1&
#110000000
0&
#110500000
b100111 N
b100111 S
b100111 M
b101000 R
b101000 T
b101000 U
1&
#111000000
0&
#111500000
b100110 N
b100110 S
b100110 M
b100111 R
b100111 T
b100111 U
1&
#112000000
0&
#112500000
b100101 N
b100101 S
b100101 M
b100110 R
b100110 T
b100110 U
1&
#113000000
0&
#113500000
b100100 N
b100100 S
b100100 M
b100101 R
b100101 T
b100101 U
1&
#114000000
0&
#114500000
b100011 N
b100011 S
b100011 M
b100100 R
b100100 T
b100100 U
1&
#115000000
0&
#115500000
b100010 N
b100010 S
b100010 M
b100011 R
b100011 T
b100011 U
1&
#116000000
0&
#116500000
b100001 N
b100001 S
b100001 M
b100010 R
b100010 T
b100010 U
1&
#117000000
0&
#117500000
b100000 N
b100000 S
b100000 M
b100001 R
b100001 T
b100001 U
1&
#118000000
0&
#118500000
b11111 N
b11111 S
b11111 M
b100000 R
b100000 T
b100000 U
1&
#119000000
0&
#119500000
b11110 N
b11110 S
b11110 M
b11111 R
b11111 T
b11111 U
1&
#120000000
0&
#120500000
b11101 N
b11101 S
b11101 M
b11110 R
b11110 T
b11110 U
1&
#121000000
0&
#121500000
b11100 N
b11100 S
b11100 M
b11101 R
b11101 T
b11101 U
1&
#122000000
0&
#122500000
b11011 N
b11011 S
b11011 M
b11100 R
b11100 T
b11100 U
1&
#123000000
0&
#123500000
b11010 N
b11010 S
b11010 M
b11011 R
b11011 T
b11011 U
1&
#124000000
0&
#124500000
b11001 N
b11001 S
b11001 M
b11010 R
b11010 T
b11010 U
1&
#125000000
0&
#125500000
b11000 N
b11000 S
b11000 M
b11001 R
b11001 T
b11001 U
1&
#126000000
0&
#126500000
b10111 N
b10111 S
b10111 M
b11000 R
b11000 T
b11000 U
1&
#127000000
0&
#127500000
b10110 N
b10110 S
b10110 M
b10111 R
b10111 T
b10111 U
1&
#128000000
0&
#128500000
b10101 N
b10101 S
b10101 M
b10110 R
b10110 T
b10110 U
1&
#129000000
0&
#129500000
b10100 N
b10100 S
b10100 M
b10101 R
b10101 T
b10101 U
1&
#130000000
0&
#130500000
b10011 N
b10011 S
b10011 M
b10100 R
b10100 T
b10100 U
1&
#131000000
0&
#131500000
b10010 N
b10010 S
b10010 M
b10011 R
b10011 T
b10011 U
1&
#132000000
0&
#132500000
b10001 N
b10001 S
b10001 M
b10010 R
b10010 T
b10010 U
1&
#133000000
0&
#133500000
b10000 N
b10000 S
b10000 M
b10001 R
b10001 T
b10001 U
1&
#134000000
0&
#134500000
b1111 N
b1111 S
b1111 M
b10000 R
b10000 T
b10000 U
1&
#135000000
0&
#135500000
b1110 N
b1110 S
b1110 M
b1111 R
b1111 T
b1111 U
1&
#136000000
0&
#136500000
b1101 N
b1101 S
b1101 M
b1110 R
b1110 T
b1110 U
1&
#137000000
0&
#137500000
b1100 N
b1100 S
b1100 M
b1101 R
b1101 T
b1101 U
1&
#138000000
0&
#138500000
b1011 N
b1011 S
b1011 M
b1100 R
b1100 T
b1100 U
1&
#139000000
0&
#139500000
b1010 N
b1010 S
b1010 M
b1011 R
b1011 T
b1011 U
1&
#140000000
0&
#140500000
b1001 N
b1001 S
b1001 M
b1010 R
b1010 T
b1010 U
1&
#141000000
0&
#141500000
b1000 N
b1000 S
b1000 M
b1001 R
b1001 T
b1001 U
1&
#142000000
0&
#142500000
b111 N
b111 S
b111 M
b1000 R
b1000 T
b1000 U
1&
#143000000
0&
#143500000
b110 N
b110 S
b110 M
b111 R
b111 T
b111 U
1&
#144000000
0&
#144500000
b101 N
b101 S
b101 M
b110 R
b110 T
b110 U
1&
#145000000
0&
#145500000
b100 N
b100 S
b100 M
b101 R
b101 T
b101 U
1&
#146000000
0&
#146500000
b11 N
b11 S
b11 M
b100 R
b100 T
b100 U
1&
#147000000
0&
#147500000
b10 N
b10 S
b10 M
b11 R
b11 T
b11 U
1&
#148000000
0&
#148500000
b1 N
b1 S
b1 M
b10 R
b10 T
b10 U
1&
#149000000
1"
0$
1;
0?
b101 8
b1010000 Q
b1010000 C
b1010000 O
0&
b10100000000000000000101 '
b10100000000000000000101 ,
#149500000
b0 N
b0 S
b0 M
b1 R
b1 T
b1 U
1&
#150000000
0&
#150500000
b11 6
b11 J
01
b11111111111111111 N
b11111111111111111 S
02
0.
b11111111111111111 M
1+
0"
10
1B
b0 R
b0 T
b0 U
1&
#151000000
0&
#151500000
b1010000 N
b1010000 S
11
12
b11 6
b11 J
0+
1"
1/
1)
1P
00
0B
b11111111111111111 R
b11111111111111111 T
b11111111111111111 U
b11 !
b11 7
b11 K
b11 L
04
1&
#152000000
0&
#152500000
11
b1001111 N
b1001111 S
1.
b1001111 M
0/
0)
0P
b1010000 R
b1010000 T
b1010000 U
14
1&
#153000000
0&
#153500000
b1001110 N
b1001110 S
b1001110 M
b1001111 R
b1001111 T
b1001111 U
1&
#154000000
0&
