dff.v
// ===========================================================================
//
// Description:
//  Verilog module sirv_gnrl DFF with Load-enable and Reset
//  Default reset value is 1
//
// ===========================================================================
module dfflrs # (
  parameter DW = 32
) (

  input               lden, 
  input      [DW-1:0] dnxt,
  output     [DW-1:0] qout,

  input               clk,
  input               rst_n
);

reg [DW-1:0] qout_r;

always @(posedge clk or negedge rst_n)
begin : DFFLRS_PROC
  if (rst_n == 1'b0)
    qout_r <= {DW{1'b1}};
  else if (lden == 1'b1)
    qout_r <= dnxt;
end

assign qout = qout_r;


endmodule
// ===========================================================================
//
// Description:
//  Verilog module sirv_gnrl DFF with Load-enable and Reset
//  Default reset value is 0
//
// ===========================================================================

module dfflr # (
  parameter DW = 32
) (

  input               lden, 
  input      [DW-1:0] dnxt,
  output     [DW-1:0] qout,

  input               clk,
  input               rst_n
);

reg [DW-1:0] qout_r;

always @(posedge clk or negedge rst_n)
begin : DFFLR_PROC
  if (rst_n == 1'b0)
    qout_r <= {DW{1'b0}};
  else if (lden == 1'b1)
    qout_r <= #1 dnxt;
end

assign qout = qout_r;


endmodule
// ===========================================================================
//
// Description:
//  Verilog module sirv_gnrl DFF with Load-enable, no reset 
//
// ===========================================================================

module dffl # (
  parameter DW = 32
) (

  input               lden, 
  input      [DW-1:0] dnxt,
  output     [DW-1:0] qout,

  input               clk 
);

reg [DW-1:0] qout_r;

always @(posedge clk)
begin : DFFL_PROC
  if (lden == 1'b1)
    qout_r <= #1 dnxt;
end

assign qout = qout_r;


endmodule
// ===========================================================================
//
// Description:
//  Verilog module sirv_gnrl DFF with Reset, no load-enable
//  Default reset value is 1
//
// ===========================================================================

module dffrs # (
  parameter DW = 32
) (

  input      [DW-1:0] dnxt,
  output     [DW-1:0] qout,

  input               clk,
  input               rst_n
);

reg [DW-1:0] qout_r;

always @(posedge clk or negedge rst_n)
begin : DFFRS_PROC
  if (rst_n == 1'b0)
    qout_r <= {DW{1'b1}};
  else                  
    qout_r <= dnxt;
end

assign qout = qout_r;

endmodule
// ===========================================================================
//
// Description:
//  Verilog module sirv_gnrl DFF with Reset, no load-enable
//  Default reset value is 0
//
// ===========================================================================

module dffr # (
  parameter DW = 32
) (

  input      [DW-1:0] dnxt,
  output     [DW-1:0] qout,

  input               clk,
  input               rst_n
);

reg [DW-1:0] qout_r;

always @(posedge clk or negedge rst_n)
begin : DFFR_PROC
  if (rst_n == 1'b0)
    qout_r <= {DW{1'b0}};
  else                  
    qout_r <= dnxt;
end

assign qout = qout_r;

endmodule
// ===========================================================================
//
// Description:
//  Verilog module for general latch 
//
// ===========================================================================

module sirv_gnrl_ltch # (
  parameter DW = 32
) (

  //input               test_mode,
  input               lden, 
  input      [DW-1:0] dnxt,
  output     [DW-1:0] qout
);

reg [DW-1:0] qout_r;

always @ (*) 
begin : LTCH_PROC
  if (lden == 1'b1)
    qout_r <= dnxt;
end

//assign qout = test_mode ? dnxt : qout_r;
assign qout = qout_r;


endmodule

timer.v
module timer # (
  parameter WIDTH = 16
) (
  input [WIDTH-1:0] set,
  input       load,
  output      irq,

  input clk,
  input rst_n
);

wire [WIDTH:0] cnt;
wire [WIDTH:0] cnt_next;
wire [WIDTH:0] cnt_next_or_load;
wire sign = cnt[WIDTH];

assign irq = cnt == 17'd0;

wire [WIDTH:0] set_ext;
assign set_ext = {1'b0, set};

assign cnt_next =
    ({(WIDTH+1){~sign}} & (cnt - 17'd1))
  | ({(WIDTH+1){ sign}} & 17'h1ffff);

assign cnt_next_or_load =
    ({(WIDTH+1){ load}} & set_ext)
  | ({(WIDTH+1){~load}} & cnt_next);

dffrs #(WIDTH+1) timer_dff (
  .dnxt(cnt_next_or_load),
  .qout(cnt),
  .clk(clk),
  .rst_n(rst_n)
);

endmodule

processor.v
module processor # (
  parameter OPCODE_WIDTH = 8,
  parameter REG_WIDTH = 8,
  parameter IMME_WIDTH = 16,
  parameter INSTRS_WIDTH = 32,
  parameter ADDR_WIDTH = 8,
  parameter REG_NUM = 2,
  parameter BOOT_ADDR = 8'd2
) (
  input                     ena,
  input                     start,
  input  [INSTRS_WIDTH-1:0] instr,
  output   [ADDR_WIDTH-1:0] pc,

  output ctrl_fill,
  output ctrl_release,
  output ctrl_forward,
  output ctrl_reverse,

  input clk,
  input rst_n
);

localparam op_halt    = 8'h00;
localparam op_wait    = 8'h11;
localparam op_fill    = 8'h12;
localparam op_release = 8'h13;
localparam op_forward = 8'h14;
localparam op_reverse = 8'h15;
localparam op_set     = 8'h21;
localparam op_dec     = 8'h22;
localparam op_j       = 8'h30;
localparam op_jz      = 8'h31;
localparam op_jnz     = 8'h32;

wire op_is_halt;
wire op_is_wait;
wire op_is_fill;
wire op_is_release;
wire op_is_forward;
wire op_is_reverse;
wire op_is_set;
wire op_is_dec;
wire op_is_j;
wire op_is_jz;
wire op_is_jnz;

assign op_is_halt    = opcode == op_halt;
assign op_is_wait    = opcode == op_wait;
assign op_is_fill    = opcode == op_fill;
assign op_is_release = opcode == op_release;
assign op_is_forward = opcode == op_forward;
assign op_is_reverse = opcode == op_reverse;
assign op_is_set     = opcode == op_set;
assign op_is_dec     = opcode == op_dec;
assign op_is_j       = opcode == op_j;
assign op_is_jz      = opcode == op_jz;
assign op_is_jnz     = opcode == op_jnz;


wire [7:0] opcode;
wire [7:0] reg_id;
wire [15:0] arg;

assign opcode = instr[7:0];
assign reg_id = instr[15:8];
assign arg = instr[31:16];

wire sleep;
wire sleep_next;
wire sleep_instr;
wire sleep_exit_ena;
wire active_exit_ena;
wire keep_state;

assign sleep_instr =
  opcode[7:4] == 4'd1;
assign active_exit_ena =
  (~sleep) & sleep_instr;
assign sleep_exit_ena =
  sleep & irq;
assign keep_state =
  ~active_exit_ena & ~sleep_exit_ena;

assign sleep_next =
    (active_exit_ena & 1'b1)
  | (sleep_exit_ena  & 1'b0)
  | (keep_state      & sleep);

dffr #(1) sleep_dff (
  .dnxt(sleep_next),
  .qout(sleep),
  .clk(clk),
  .rst_n(rst_n)
);

assign ctrl_fill    = ~irq & op_is_fill;
assign ctrl_release = ~irq & op_is_release;
assign ctrl_forward = ~irq & op_is_forward;
assign ctrl_reverse = ~irq & op_is_reverse;

wire [15:0] var [0:REG_NUM-1];
wire [15:0] var_next [0:REG_NUM-1];
wire var_set [0:REG_NUM-1];
wire var_dec [0:REG_NUM-1];
wire var_keep [0:REG_NUM-1];

genvar i;
generate
  for (i = 0; i < REG_NUM; i = i + 1) begin : var_loop
    assign var_set[i] = (reg_id == i) & op_is_set;
    assign var_dec[i] = (reg_id == i) & op_is_dec;
    assign var_keep[i] = ~var_set[i] & ~var_dec[i];
    assign var_next[i] =
        ({16{ var_set[i]}} & arg)
      | ({16{ var_dec[i]}} & (var[i] - 16'd1))
      | ({16{var_keep[i]}} & var[i]);
    dffr #(16) var_dff (
      .dnxt(var_next[i]),
      .qout(var[i]),
      .clk(clk),
      .rst_n(rst_n)
    );
  end
endgenerate

wire [7:0] pc;
wire [7:0] pc_next;

wire fetch;
wire jump;
wire stay;

assign jump =
    (op_is_jz  & (var[reg_id] == 16'd0))
  | (op_is_jnz & (var[reg_id] != 16'd0))
  | op_is_j;
assign fetch =
    ( sleep_instr & irq)
  | (~sleep_instr & ~jump & ~op_is_halt);
assign boot =
  op_is_halt & start;
assign stay =
  ~jump & ~fetch & ~boot;

assign pc_next =
    ({8{jump }} & arg)
  | ({8{fetch}} & pc + 8'd1)
  | ({8{boot }} & BOOT_ADDR)
  | ({8{stay }} & pc);

dffr #(8) pc_dff (
  .dnxt(pc_next),
  .qout(pc),
  .clk(clk),
  .rst_n(rst_n)
);

wire load;
wire irq;
assign load = sleep_instr & ~sleep;
timer timer0 (
  .set(arg),
  .load(load),
  .irq(irq),
  .clk(clk),
  .rst_n(rst_n)
);

endmodule

rom.v
module rom # (
  parameter INSTRS_WIDTH = 32,
  parameter ADDR_WIDTH = 8,
  parameter ROM_SIZE = 64
) (
  input    [ADDR_WIDTH-1:0] pc,
  output [INSTRS_WIDTH-1:0] instr
);

reg [INSTRS_WIDTH-1:0] mem [0:ROM_SIZE-1];

assign instr = mem[pc];

localparam op_halt    = 8'h00;
localparam op_wait    = 8'h01;
localparam op_fill    = 8'h02;
localparam op_release = 8'h03;
localparam op_forward = 8'h04;
localparam op_reverse = 8'h05;
localparam op_set     = 8'h11;
localparam op_dec     = 8'h12;
localparam op_jz      = 8'h21;
localparam op_jnz     = 8'h22;

integer i;
initial begin
  for (i = 0; i < 64; i++)
    mem[i] = 32'h0000;

  mem[02] = {16'd100, 8'd00, op_fill};
  mem[03] = {16'd050, 8'd00, op_wait};
  mem[04] = {16'd005, 8'd00, op_set};
  // loop start
  mem[05] = {16'd020, 8'd00, op_forward};
  mem[06] = {16'd010, 8'd00, op_wait};
  mem[07] = {16'd020, 8'd00, op_reverse};
  mem[08] = {16'd010, 8'd00, op_wait};
  mem[09] = {16'd000, 8'd00, op_dec};
  mem[10] = {16'd005, 8'd00, op_jnz};
  // loop end
  mem[11] = {16'd100, 8'd00, op_release};
end

endmodule

reg_machine.v
module reg_machine # (
  parameter INSTRS_WIDTH = 32,
  parameter ADDR_WIDTH = 8
) (
  input start,

  output ctrl_fill,
  output ctrl_release,
  output ctrl_forward,
  output ctrl_reverse,

  input clk,
  input rst_n
);

wire [ADDR_WIDTH-1:0] pc;
wire [INSTRS_WIDTH-1:0] instr;

rom rom0 (
  .pc(pc),
  .instr(instr)
);

processor processor0 (
  .ena(1'b1),
  .instr(instr),
  .pc(pc),
  .ctrl_fill(ctrl_fill),
  .ctrl_release(ctrl_release),
  .ctrl_forward(ctrl_forward),
  .ctrl_reverse(ctrl_reverse),
  .clk(clk),
  .rst_n(rst_n)
);

endmodule

reg_machine_test.v
`timescale 100ms/1ns
module reg_machine_test;

reg clk;
reg rst_n;

initial begin
    $dumpfile("reg_machine_test.vcd");
    $dumpvars(0, reg_machine_test);
end

always #(0.5)
  clk = ~clk;

initial begin
  clk <= 1'b0;
  rst_n <= 1'b0;
  #(2) rst_n <= 1'b1;
end

reg start = 1'd0;
wire ctrl_fill;
wire ctrl_release;
wire ctrl_forward;
wire ctrl_reverse;

reg_machine reg_machine0 (
  .start(start),
  .ctrl_fill(ctrl_fill),
  .ctrl_release(ctrl_release),
  .ctrl_forward(ctrl_forward),
  .ctrl_reverse(ctrl_reverse),
  .clk(clk),
  .rst_n(rst_n)
);

initial begin
  #(128) start <= 1'd1;
  #(2) start <= 1'd0;
  #(64) start <= 1'd1;
  #(2) start <= 1'd0;
  #(4096) $finish;
end

endmodule

reg_machine_test.vcd
$date
	Thu Mar  2 20:57:35 2023
$end
$version
	Icarus Verilog
$end
$timescale
	1ns
$end
$scope module reg_machine_test $end
$var wire 1 ! ctrl_reverse $end
$var wire 1 " ctrl_release $end
$var wire 1 # ctrl_forward $end
$var wire 1 $ ctrl_fill $end
$var reg 1 % clk $end
$var reg 1 & rst_n $end
$var reg 1 ' start $end
$scope module reg_machine0 $end
$var wire 1 % clk $end
$var wire 1 & rst_n $end
$var wire 1 ' start $end
$var wire 8 ( pc [7:0] $end
$var wire 32 ) instr [31:0] $end
$var wire 1 ! ctrl_reverse $end
$var wire 1 " ctrl_release $end
$var wire 1 # ctrl_forward $end
$var wire 1 $ ctrl_fill $end
$scope module processor0 $end
$var wire 1 * active_exit_ena $end
$var wire 1 + boot $end
$var wire 1 % clk $end
$var wire 1 $ ctrl_fill $end
$var wire 1 # ctrl_forward $end
$var wire 1 " ctrl_release $end
$var wire 1 ! ctrl_reverse $end
$var wire 1 , ena $end
$var wire 1 - fetch $end
$var wire 1 . jump $end
$var wire 1 / keep_state $end
$var wire 1 0 load $end
$var wire 1 & rst_n $end
$var wire 1 1 sleep_exit_ena $end
$var wire 1 2 sleep_next $end
$var wire 1 ' start $end
$var wire 1 3 stay $end
$var wire 1 4 sleep_instr $end
$var wire 1 5 sleep $end
$var wire 8 6 reg_id [7:0] $end
$var wire 8 7 pc_next [7:0] $end
$var wire 8 8 pc [7:0] $end
$var wire 8 9 opcode [7:0] $end
$var wire 1 : op_is_wait $end
$var wire 1 ; op_is_set $end
$var wire 1 < op_is_reverse $end
$var wire 1 = op_is_release $end
$var wire 1 > op_is_jz $end
$var wire 1 ? op_is_jnz $end
$var wire 1 @ op_is_j $end
$var wire 1 A op_is_halt $end
$var wire 1 B op_is_forward $end
$var wire 1 C op_is_fill $end
$var wire 1 D op_is_dec $end
$var wire 1 E irq $end
$var wire 32 F instr [31:0] $end
$var wire 16 G arg [15:0] $end
$scope begin var_loop[0] $end
$scope module var_dff $end
$var wire 1 % clk $end
$var wire 16 H dnxt [15:0] $end
$var wire 1 & rst_n $end
$var wire 16 I qout [15:0] $end
$var reg 16 J qout_r [15:0] $end
$scope begin DFFR_PROC $end
$upscope $end
$upscope $end
$upscope $end
$scope begin var_loop[1] $end
$scope module var_dff $end
$var wire 1 % clk $end
$var wire 16 K dnxt [15:0] $end
$var wire 1 & rst_n $end
$var wire 16 L qout [15:0] $end
$var reg 16 M qout_r [15:0] $end
$scope begin DFFR_PROC $end
$upscope $end
$upscope $end
$upscope $end
$scope module pc_dff $end
$var wire 1 % clk $end
$var wire 8 N dnxt [7:0] $end
$var wire 1 & rst_n $end
$var wire 8 O qout [7:0] $end
$var reg 8 P qout_r [7:0] $end
$scope begin DFFR_PROC $end
$upscope $end
$upscope $end
$scope module sleep_dff $end
$var wire 1 % clk $end
$var wire 1 2 dnxt $end
$var wire 1 & rst_n $end
$var wire 1 5 qout $end
$var reg 1 5 qout_r $end
$scope begin DFFR_PROC $end
$upscope $end
$upscope $end
$scope module timer0 $end
$var wire 1 % clk $end
$var wire 17 Q cnt_next [16:0] $end
$var wire 17 R cnt_next_or_load [16:0] $end
$var wire 1 0 load $end
$var wire 1 & rst_n $end
$var wire 16 S set [15:0] $end
$var wire 1 T sign $end
$var wire 17 U set_ext [16:0] $end
$var wire 1 E irq $end
$var wire 17 V cnt [16:0] $end
$scope module timer_dff $end
$var wire 1 % clk $end
$var wire 17 W dnxt [16:0] $end
$var wire 1 & rst_n $end
$var wire 17 X qout [16:0] $end
$var reg 17 Y qout_r [16:0] $end
$scope begin DFFRS_PROC $end
$upscope $end
$upscope $end
$upscope $end
$upscope $end
$scope module rom0 $end
$var wire 32 Z instr [31:0] $end
$var wire 8 [ pc [7:0] $end
$var integer 32 \ i [31:0] $end
$upscope $end
$upscope $end
$upscope $end
$enddefinitions $end
#0
$dumpvars
b1000000 \
b0 [
b0 Z
b11111111111111111 Y
b11111111111111111 X
b11111111111111111 W
b11111111111111111 V
b0 U
1T
b0 S
b11111111111111111 R
b11111111111111111 Q
b0 P
b0 O
b0 N
b0 M
b0 L
b0 K
b0 J
b0 I
b0 H
b0 G
b0 F
0E
0D
0C
0B
1A
0@
0?
0>
0=
0<
0;
0:
b0 9
b0 8
b0 7
b0 6
05
04
13
02
01
00
1/
0.
0-
1,
0+
0*
b0 )
b0 (
0'
0&
0%
0$
0#
0"
0!
$end
#50000000
1%
#100000000
0%
#150000000
1%
#200000000
1&
0%
#250000000
1%
#300000000
0%
#350000000
1%
#400000000
0%
#450000000
1%
#500000000
0%
#550000000
1%
#600000000
0%
#650000000
1%
#700000000
0%
#750000000
1%
#800000000
0%
#850000000
1%
#900000000
0%
#950000000
1%
#1000000000
0%
#1050000000
1%
#1100000000
0%
#1150000000
1%
#1200000000
0%
#1250000000
1%
#1300000000
0%
#1350000000
1%
#1400000000
0%
#1450000000
1%
#1500000000
0%
#1550000000
1%
#1600000000
0%
#1650000000
1%
#1700000000
0%
#1750000000
1%
#1800000000
0%
#1850000000
1%
#1900000000
0%
#1950000000
1%
#2000000000
0%
#2050000000
1%
#2100000000
0%
#2150000000
1%
#2200000000
0%
#2250000000
1%
#2300000000
0%
#2350000000
1%
#2400000000
0%
#2450000000
1%
#2500000000
0%
#2550000000
1%
#2600000000
0%
#2650000000
1%
#2700000000
0%
#2750000000
1%
#2800000000
0%
#2850000000
1%
#2900000000
0%
#2950000000
1%
#3000000000
0%
#3050000000
1%
#3100000000
0%
#3150000000
1%
#3200000000
0%
#3250000000
1%
#3300000000
0%
#3350000000
1%
#3400000000
0%
#3450000000
1%
#3500000000
0%
#3550000000
1%
#3600000000
0%
#3650000000
1%
#3700000000
0%
#3750000000
1%
#3800000000
0%
#3850000000
1%
#3900000000
0%
#3950000000
1%
#4000000000
0%
#4050000000
1%
#4100000000
0%
#4150000000
1%
#4200000000
0%
#4250000000
1%
#4300000000
0%
#4350000000
1%
#4400000000
0%
#4450000000
1%
#4500000000
0%
#4550000000
1%
#4600000000
0%
#4650000000
1%
#4700000000
0%
#4750000000
1%
#4800000000
0%
#4850000000
1%
#4900000000
0%
#4950000000
1%
#5000000000
0%
#5050000000
1%
#5100000000
0%
#5150000000
1%
#5200000000
0%
#5250000000
1%
#5300000000
0%
#5350000000
1%
#5400000000
0%
#5450000000
1%
#5500000000
0%
#5550000000
1%
#5600000000
0%
#5650000000
1%
#5700000000
0%
#5750000000
1%
#5800000000
0%
#5850000000
1%
#5900000000
0%
#5950000000
1%
#6000000000
0%
#6050000000
1%
#6100000000
0%
#6150000000
1%
#6200000000
0%
#6250000000
1%
#6300000000
0%
#6350000000
1%
#6400000000
0%
#6450000000
1%
#6500000000
0%
#6550000000
1%
#6600000000
0%
#6650000000
1%
#6700000000
0%
#6750000000
1%
#6800000000
0%
#6850000000
1%
#6900000000
0%
#6950000000
1%
#7000000000
0%
#7050000000
1%
#7100000000
0%
#7150000000
1%
#7200000000
0%
#7250000000
1%
#7300000000
0%
#7350000000
1%
#7400000000
0%
#7450000000
1%
#7500000000
0%
#7550000000
1%
#7600000000
0%
#7650000000
1%
#7700000000
0%
#7750000000
1%
#7800000000
0%
#7850000000
1%
#7900000000
0%
#7950000000
1%
#8000000000
0%
#8050000000
1%
#8100000000
0%
#8150000000
1%
#8200000000
0%
#8250000000
1%
#8300000000
0%
#8350000000
1%
#8400000000
0%
#8450000000
1%
#8500000000
0%
#8550000000
1%
#8600000000
0%
#8650000000
1%
#8700000000
0%
#8750000000
1%
#8800000000
0%
#8850000000
1%
#8900000000
0%
#8950000000
1%
#9000000000
0%
#9050000000
1%
#9100000000
0%
#9150000000
1%
#9200000000
0%
#9250000000
1%
#9300000000
0%
#9350000000
1%
#9400000000
0%
#9450000000
1%
#9500000000
0%
#9550000000
1%
#9600000000
0%
#9650000000
1%
#9700000000
0%
#9750000000
1%
#9800000000
0%
#9850000000
1%
#9900000000
0%
#9950000000
1%
#10000000000
0%
#10050000000
1%
#10100000000
0%
#10150000000
1%
#10200000000
0%
#10250000000
1%
#10300000000
0%
#10350000000
1%
#10400000000
0%
#10450000000
1%
#10500000000
0%
#10550000000
1%
#10600000000
0%
#10650000000
1%
#10700000000
0%
#10750000000
1%
#10800000000
0%
#10850000000
1%
#10900000000
0%
#10950000000
1%
#11000000000
0%
#11050000000
1%
#11100000000
0%
#11150000000
1%
#11200000000
0%
#11250000000
1%
#11300000000
0%
#11350000000
1%
#11400000000
0%
#11450000000
1%
#11500000000
0%
#11550000000
1%
#11600000000
0%
#11650000000
1%
#11700000000
0%
#11750000000
1%
#11800000000
0%
#11850000000
1%
#11900000000
0%
#11950000000
1%
#12000000000
0%
#12050000000
1%
#12100000000
0%
#12150000000
1%
#12200000000
0%
#12250000000
1%
#12300000000
0%
#12350000000
1%
#12400000000
0%
#12450000000
1%
#12500000000
0%
#12550000000
1%
#12600000000
0%
#12650000000
1%
#12700000000
0%
#12750000000
1%
#12800000000
b10 7
b10 N
03
1+
1'
0%
#12850000000
b1100100 R
b1100100 W
12
b10 7
b10 N
0/
13
0-
10
1*
14
1$
0+
b1100100 U
b1100100 G
b1100100 S
1C
0A
b10010 9
b11001000000000000010010 )
b11001000000000000010010 F
b11001000000000000010010 Z
b10 (
b10 8
b10 O
b10 P
b10 [
1%
#12900000000
0%
#12950000000
12
b1100011 R
b1100011 W
1/
b1100011 Q
00
0*
0T
b1100100 V
b1100100 X
b1100100 Y
15
1%
#13000000000
0'
0%
#13050000000
b1100010 R
b1100010 W
b1100010 Q
b1100011 V
b1100011 X
b1100011 Y
1%
#13100000000
0%
#13150000000
b1100001 R
b1100001 W
b1100001 Q
b1100010 V
b1100010 X
b1100010 Y
1%
#13200000000
0%
#13250000000
b1100000 R
b1100000 W
b1100000 Q
b1100001 V
b1100001 X
b1100001 Y
1%
#13300000000
0%
#13350000000
b1011111 R
b1011111 W
b1011111 Q
b1100000 V
b1100000 X
b1100000 Y
1%
#13400000000
0%
#13450000000
b1011110 R
b1011110 W
b1011110 Q
b1011111 V
b1011111 X
b1011111 Y
1%
#13500000000
0%
#13550000000
b1011101 R
b1011101 W
b1011101 Q
b1011110 V
b1011110 X
b1011110 Y
1%
#13600000000
0%
#13650000000
b1011100 R
b1011100 W
b1011100 Q
b1011101 V
b1011101 X
b1011101 Y
1%
#13700000000
0%
#13750000000
b1011011 R
b1011011 W
b1011011 Q
b1011100 V
b1011100 X
b1011100 Y
1%
#13800000000
0%
#13850000000
b1011010 R
b1011010 W
b1011010 Q
b1011011 V
b1011011 X
b1011011 Y
1%
#13900000000
0%
#13950000000
b1011001 R
b1011001 W
b1011001 Q
b1011010 V
b1011010 X
b1011010 Y
1%
#14000000000
0%
#14050000000
b1011000 R
b1011000 W
b1011000 Q
b1011001 V
b1011001 X
b1011001 Y
1%
#14100000000
0%
#14150000000
b1010111 R
b1010111 W
b1010111 Q
b1011000 V
b1011000 X
b1011000 Y
1%
#14200000000
0%
#14250000000
b1010110 R
b1010110 W
b1010110 Q
b1010111 V
b1010111 X
b1010111 Y
1%
#14300000000
0%
#14350000000
b1010101 R
b1010101 W
b1010101 Q
b1010110 V
b1010110 X
b1010110 Y
1%
#14400000000
0%
#14450000000
b1010100 R
b1010100 W
b1010100 Q
b1010101 V
b1010101 X
b1010101 Y
1%
#14500000000
0%
#14550000000
b1010011 R
b1010011 W
b1010011 Q
b1010100 V
b1010100 X
b1010100 Y
1%
#14600000000
0%
#14650000000
b1010010 R
b1010010 W
b1010010 Q
b1010011 V
b1010011 X
b1010011 Y
1%
#14700000000
0%
#14750000000
b1010001 R
b1010001 W
b1010001 Q
b1010010 V
b1010010 X
b1010010 Y
1%
#14800000000
0%
#14850000000
b1010000 R
b1010000 W
b1010000 Q
b1010001 V
b1010001 X
b1010001 Y
1%
#14900000000
0%
#14950000000
b1001111 R
b1001111 W
b1001111 Q
b1010000 V
b1010000 X
b1010000 Y
1%
#15000000000
0%
#15050000000
b1001110 R
b1001110 W
b1001110 Q
b1001111 V
b1001111 X
b1001111 Y
1%
#15100000000
0%
#15150000000
b1001101 R
b1001101 W
b1001101 Q
b1001110 V
b1001110 X
b1001110 Y
1%
#15200000000
0%
#15250000000
b1001100 R
b1001100 W
b1001100 Q
b1001101 V
b1001101 X
b1001101 Y
1%
#15300000000
0%
#15350000000
b1001011 R
b1001011 W
b1001011 Q
b1001100 V
b1001100 X
b1001100 Y
1%
#15400000000
0%
#15450000000
b1001010 R
b1001010 W
b1001010 Q
b1001011 V
b1001011 X
b1001011 Y
1%
#15500000000
0%
#15550000000
b1001001 R
b1001001 W
b1001001 Q
b1001010 V
b1001010 X
b1001010 Y
1%
#15600000000
0%
#15650000000
b1001000 R
b1001000 W
b1001000 Q
b1001001 V
b1001001 X
b1001001 Y
1%
#15700000000
0%
#15750000000
b1000111 R
b1000111 W
b1000111 Q
b1001000 V
b1001000 X
b1001000 Y
1%
#15800000000
0%
#15850000000
b1000110 R
b1000110 W
b1000110 Q
b1000111 V
b1000111 X
b1000111 Y
1%
#15900000000
0%
#15950000000
b1000101 R
b1000101 W
b1000101 Q
b1000110 V
b1000110 X
b1000110 Y
1%
#16000000000
0%
#16050000000
b1000100 R
b1000100 W
b1000100 Q
b1000101 V
b1000101 X
b1000101 Y
1%
#16100000000
0%
#16150000000
b1000011 R
b1000011 W
b1000011 Q
b1000100 V
b1000100 X
b1000100 Y
1%
#16200000000
0%
#16250000000
b1000010 R
b1000010 W
b1000010 Q
b1000011 V
b1000011 X
b1000011 Y
1%
#16300000000
0%
#16350000000
b1000001 R
b1000001 W
b1000001 Q
b1000010 V
b1000010 X
b1000010 Y
1%
#16400000000
0%
#16450000000
b1000000 R
b1000000 W
b1000000 Q
b1000001 V
b1000001 X
b1000001 Y
1%
#16500000000
0%
#16550000000
b111111 R
b111111 W
b111111 Q
b1000000 V
b1000000 X
b1000000 Y
1%
#16600000000
0%
#16650000000
b111110 R
b111110 W
b111110 Q
b111111 V
b111111 X
b111111 Y
1%
#16700000000
0%
#16750000000
b111101 R
b111101 W
b111101 Q
b111110 V
b111110 X
b111110 Y
1%
#16800000000
0%
#16850000000
b111100 R
b111100 W
b111100 Q
b111101 V
b111101 X
b111101 Y
1%
#16900000000
0%
#16950000000
b111011 R
b111011 W
b111011 Q
b111100 V
b111100 X
b111100 Y
1%
#17000000000
0%
#17050000000
b111010 R
b111010 W
b111010 Q
b111011 V
b111011 X
b111011 Y
1%
#17100000000
0%
#17150000000
b111001 R
b111001 W
b111001 Q
b111010 V
b111010 X
b111010 Y
1%
#17200000000
0%
#17250000000
b111000 R
b111000 W
b111000 Q
b111001 V
b111001 X
b111001 Y
1%
#17300000000
0%
#17350000000
b110111 R
b110111 W
b110111 Q
b111000 V
b111000 X
b111000 Y
1%
#17400000000
0%
#17450000000
b110110 R
b110110 W
b110110 Q
b110111 V
b110111 X
b110111 Y
1%
#17500000000
0%
#17550000000
b110101 R
b110101 W
b110101 Q
b110110 V
b110110 X
b110110 Y
1%
#17600000000
0%
#17650000000
b110100 R
b110100 W
b110100 Q
b110101 V
b110101 X
b110101 Y
1%
#17700000000
0%
#17750000000
b110011 R
b110011 W
b110011 Q
b110100 V
b110100 X
b110100 Y
1%
#17800000000
0%
#17850000000
b110010 R
b110010 W
b110010 Q
b110011 V
b110011 X
b110011 Y
1%
#17900000000
0%
#17950000000
b110001 R
b110001 W
b110001 Q
b110010 V
b110010 X
b110010 Y
1%
#18000000000
0%
#18050000000
b110000 R
b110000 W
b110000 Q
b110001 V
b110001 X
b110001 Y
1%
#18100000000
0%
#18150000000
b101111 R
b101111 W
b101111 Q
b110000 V
b110000 X
b110000 Y
1%
#18200000000
0%
#18250000000
b101110 R
b101110 W
b101110 Q
b101111 V
b101111 X
b101111 Y
1%
#18300000000
0%
#18350000000
b101101 R
b101101 W
b101101 Q
b101110 V
b101110 X
b101110 Y
1%
#18400000000
0%
#18450000000
b101100 R
b101100 W
b101100 Q
b101101 V
b101101 X
b101101 Y
1%
#18500000000
0%
#18550000000
b101011 R
b101011 W
b101011 Q
b101100 V
b101100 X
b101100 Y
1%
#18600000000
0%
#18650000000
b101010 R
b101010 W
b101010 Q
b101011 V
b101011 X
b101011 Y
1%
#18700000000
0%
#18750000000
b101001 R
b101001 W
b101001 Q
b101010 V
b101010 X
b101010 Y
1%
#18800000000
0%
#18850000000
b101000 R
b101000 W
b101000 Q
b101001 V
b101001 X
b101001 Y
1%
#18900000000
0%
#18950000000
b100111 R
b100111 W
b100111 Q
b101000 V
b101000 X
b101000 Y
1%
#19000000000
0%
#19050000000
b100110 R
b100110 W
b100110 Q
b100111 V
b100111 X
b100111 Y
1%
#19100000000
0%
#19150000000
b100101 R
b100101 W
b100101 Q
b100110 V
b100110 X
b100110 Y
1%
#19200000000
0%
#19250000000
b100100 R
b100100 W
b100100 Q
b100101 V
b100101 X
b100101 Y
1%
#19300000000
0%
#19350000000
b100011 R
b100011 W
b100011 Q
b100100 V
b100100 X
b100100 Y
1%
#19400000000
1'
0%
#19450000000
b100010 R
b100010 W
b100010 Q
b100011 V
b100011 X
b100011 Y
1%
#19500000000
0%
#19550000000
b100001 R
b100001 W
b100001 Q
b100010 V
b100010 X
b100010 Y
1%
#19600000000
0'
0%
#19650000000
b100000 R
b100000 W
b100000 Q
b100001 V
b100001 X
b100001 Y
1%
#19700000000
0%
#19750000000
b11111 R
b11111 W
b11111 Q
b100000 V
b100000 X
b100000 Y
1%
#19800000000
0%
#19850000000
b11110 R
b11110 W
b11110 Q
b11111 V
b11111 X
b11111 Y
1%
#19900000000
0%
#19950000000
b11101 R
b11101 W
b11101 Q
b11110 V
b11110 X
b11110 Y
1%
#20000000000
0%
#20050000000
b11100 R
b11100 W
b11100 Q
b11101 V
b11101 X
b11101 Y
1%
#20100000000
0%
#20150000000
b11011 R
b11011 W
b11011 Q
b11100 V
b11100 X
b11100 Y
1%
#20200000000
0%
#20250000000
b11010 R
b11010 W
b11010 Q
b11011 V
b11011 X
b11011 Y
1%
#20300000000
0%
#20350000000
b11001 R
b11001 W
b11001 Q
b11010 V
b11010 X
b11010 Y
1%
#20400000000
0%
#20450000000
b11000 R
b11000 W
b11000 Q
b11001 V
b11001 X
b11001 Y
1%
#20500000000
0%
#20550000000
b10111 R
b10111 W
b10111 Q
b11000 V
b11000 X
b11000 Y
1%
#20600000000
0%
#20650000000
b10110 R
b10110 W
b10110 Q
b10111 V
b10111 X
b10111 Y
1%
#20700000000
0%
#20750000000
b10101 R
b10101 W
b10101 Q
b10110 V
b10110 X
b10110 Y
1%
#20800000000
0%
#20850000000
b10100 R
b10100 W
b10100 Q
b10101 V
b10101 X
b10101 Y
1%
#20900000000
0%
#20950000000
b10011 R
b10011 W
b10011 Q
b10100 V
b10100 X
b10100 Y
1%
#21000000000
0%
#21050000000
b10010 R
b10010 W
b10010 Q
b10011 V
b10011 X
b10011 Y
1%
#21100000000
0%
#21150000000
b10001 R
b10001 W
b10001 Q
b10010 V
b10010 X
b10010 Y
1%
#21200000000
0%
#21250000000
b10000 R
b10000 W
b10000 Q
b10001 V
b10001 X
b10001 Y
1%
#21300000000
0%
