dff.v
// ===========================================================================
//
// Description:
//  Verilog module sirv_gnrl DFF with Load-enable and Reset
//  Default reset value is 1
//
// ===========================================================================
module dfflrs # (
  parameter DW = 32
) (

  input               lden, 
  input      [DW-1:0] dnxt,
  output     [DW-1:0] qout,

  input               clk,
  input               rst_n
);

reg [DW-1:0] qout_r;

always @(posedge clk or negedge rst_n)
begin : DFFLRS_PROC
  if (rst_n == 1'b0)
    qout_r <= {DW{1'b1}};
  else if (lden == 1'b1)
    qout_r <= dnxt;
end

assign qout = qout_r;


endmodule
// ===========================================================================
//
// Description:
//  Verilog module sirv_gnrl DFF with Load-enable and Reset
//  Default reset value is 0
//
// ===========================================================================

module dfflr # (
  parameter DW = 32
) (

  input               lden, 
  input      [DW-1:0] dnxt,
  output     [DW-1:0] qout,

  input               clk,
  input               rst_n
);

reg [DW-1:0] qout_r;

always @(posedge clk or negedge rst_n)
begin : DFFLR_PROC
  if (rst_n == 1'b0)
    qout_r <= {DW{1'b0}};
  else if (lden == 1'b1)
    qout_r <= #1 dnxt;
end

assign qout = qout_r;


endmodule
// ===========================================================================
//
// Description:
//  Verilog module sirv_gnrl DFF with Load-enable, no reset 
//
// ===========================================================================

module dffl # (
  parameter DW = 32
) (

  input               lden, 
  input      [DW-1:0] dnxt,
  output     [DW-1:0] qout,

  input               clk 
);

reg [DW-1:0] qout_r;

always @(posedge clk)
begin : DFFL_PROC
  if (lden == 1'b1)
    qout_r <= #1 dnxt;
end

assign qout = qout_r;


endmodule
// ===========================================================================
//
// Description:
//  Verilog module sirv_gnrl DFF with Reset, no load-enable
//  Default reset value is 1
//
// ===========================================================================

module dffrs # (
  parameter DW = 32
) (

  input      [DW-1:0] dnxt,
  output     [DW-1:0] qout,

  input               clk,
  input               rst_n
);

reg [DW-1:0] qout_r;

always @(posedge clk or negedge rst_n)
begin : DFFRS_PROC
  if (rst_n == 1'b0)
    qout_r <= {DW{1'b1}};
  else                  
    qout_r <= dnxt;
end

assign qout = qout_r;

endmodule
// ===========================================================================
//
// Description:
//  Verilog module sirv_gnrl DFF with Reset, no load-enable
//  Default reset value is 0
//
// ===========================================================================

module dffr # (
  parameter DW = 32
) (

  input      [DW-1:0] dnxt,
  output     [DW-1:0] qout,

  input               clk,
  input               rst_n
);

reg [DW-1:0] qout_r;

always @(posedge clk or negedge rst_n)
begin : DFFR_PROC
  if (rst_n == 1'b0)
    qout_r <= {DW{1'b0}};
  else                  
    qout_r <= dnxt;
end

assign qout = qout_r;

endmodule
// ===========================================================================
//
// Description:
//  Verilog module for general latch 
//
// ===========================================================================

module sirv_gnrl_ltch # (
  parameter DW = 32
) (

  //input               test_mode,
  input               lden, 
  input      [DW-1:0] dnxt,
  output     [DW-1:0] qout
);

reg [DW-1:0] qout_r;

always @ (*) 
begin : LTCH_PROC
  if (lden == 1'b1)
    qout_r <= dnxt;
end

//assign qout = test_mode ? dnxt : qout_r;
assign qout = qout_r;


endmodule

timer.v
module timer # (
  parameter WIDTH = 16
) (
  input [WIDTH-1:0] set,
  input       load,
  output      irq,

  input clk,
  input rst_n
);

wire [WIDTH:0] cnt;
wire [WIDTH:0] cnt_next;
wire [WIDTH:0] cnt_next_or_load;
wire sign = cnt[WIDTH];

assign irq = cnt == 17'd0;

wire [WIDTH:0] set_ext;
assign set_ext = {1'b0, set};

assign cnt_next =
    ({(WIDTH+1){~sign}} & (cnt - 17'd1))
  | ({(WIDTH+1){ sign}} & 17'h1ffff);

assign cnt_next_or_load =
    ({(WIDTH+1){ load}} & set_ext)
  | ({(WIDTH+1){~load}} & cnt_next);

dffrs #(WIDTH+1) timer_dff (
  .dnxt(cnt_next_or_load),
  .qout(cnt),
  .clk(clk),
  .rst_n(rst_n)
);

endmodule

processor.v
module processor # (
  parameter OPCODE_WIDTH = 8,
  parameter REG_WIDTH = 8,
  parameter IMME_WIDTH = 16,
  parameter INSTRS_WIDTH = 32,
  parameter ADDR_WIDTH = 8,
  parameter REG_NUM = 3,
  parameter BOOT_ADDR = 8'd2,
  parameter SIG_REG = 8'd2
) (
  input                     ena,
  input                     start,
  input  [INSTRS_WIDTH-1:0] instr,
  output   [ADDR_WIDTH-1:0] pc,

  output ctrl_fill,
  output ctrl_release,
  output ctrl_forward,
  output ctrl_reverse,
  output sig_done,
  output sig_clean,
  output sig_rinse,
  output sig_dry,

  input clk,
  input rst_n
);

localparam op_halt    = 8'h00;
localparam op_wait    = 8'h11;
localparam op_fill    = 8'h12;
localparam op_release = 8'h13;
localparam op_forward = 8'h14;
localparam op_reverse = 8'h15;
localparam op_set     = 8'h21;
localparam op_dec     = 8'h22;
localparam op_j       = 8'h30;
localparam op_jz      = 8'h31;
localparam op_jnz     = 8'h32;

wire op_is_halt;
wire op_is_wait;
wire op_is_fill;
wire op_is_release;
wire op_is_forward;
wire op_is_reverse;
wire op_is_set;
wire op_is_dec;
wire op_is_j;
wire op_is_jz;
wire op_is_jnz;

assign op_is_halt    = opcode == op_halt;
assign op_is_wait    = opcode == op_wait;
assign op_is_fill    = opcode == op_fill;
assign op_is_release = opcode == op_release;
assign op_is_forward = opcode == op_forward;
assign op_is_reverse = opcode == op_reverse;
assign op_is_set     = opcode == op_set;
assign op_is_dec     = opcode == op_dec;
assign op_is_j       = opcode == op_j;
assign op_is_jz      = opcode == op_jz;
assign op_is_jnz     = opcode == op_jnz;


wire [7:0] opcode;
wire [7:0] reg_id;
wire [15:0] arg;

assign opcode = instr[7:0];
assign reg_id = instr[15:8];
assign arg = instr[31:16];

wire sleep;
wire sleep_next;
wire sleep_instr;
wire sleep_exit_ena;
wire active_exit_ena;
wire keep_state;

assign sleep_instr =
  opcode[7:4] == 4'd1;
assign active_exit_ena =
  (~sleep) & sleep_instr;
assign sleep_exit_ena =
  sleep & irq;
assign keep_state =
  ~active_exit_ena & ~sleep_exit_ena;

assign sleep_next =
    (active_exit_ena & 1'b1)
  | (sleep_exit_ena  & 1'b0)
  | (keep_state      & sleep);

dffr #(1) sleep_dff (
  .dnxt(sleep_next),
  .qout(sleep),
  .clk(clk),
  .rst_n(rst_n)
);

assign ctrl_fill    = ~irq & op_is_fill;
assign ctrl_release = ~irq & op_is_release;
assign ctrl_forward = ~irq & op_is_forward;
assign ctrl_reverse = ~irq & op_is_reverse;

wire [15:0] var [0:REG_NUM-1];
wire [15:0] var_next [0:REG_NUM-1];
wire var_set [0:REG_NUM-1];
wire var_dec [0:REG_NUM-1];
wire var_keep [0:REG_NUM-1];

genvar i;
generate
  for (i = 0; i < REG_NUM; i = i + 1) begin : var_loop
    assign var_set[i] = (reg_id == i) & op_is_set;
    assign var_dec[i] = (reg_id == i) & op_is_dec;
    assign var_keep[i] = ~var_set[i] & ~var_dec[i];
    assign var_next[i] =
        ({16{ var_set[i]}} & arg)
      | ({16{ var_dec[i]}} & (var[i] - 16'd1))
      | ({16{var_keep[i]}} & var[i]);
    dffr #(16) var_dff (
      .dnxt(var_next[i]),
      .qout(var[i]),
      .clk(clk),
      .rst_n(rst_n)
    );
  end
endgenerate

wire [7:0] pc;
wire [7:0] pc_next;

wire fetch;
wire jump;
wire stay;

assign jump =
    (op_is_jz  & (var[reg_id] == 16'd0))
  | (op_is_jnz & (var[reg_id] != 16'd0))
  | op_is_j;
assign fetch =
    ( sleep_instr & irq)
  | (~sleep_instr & ~jump & ~op_is_halt);
assign boot =
  op_is_halt & start;
assign stay =
  ~jump & ~fetch & ~boot;

assign pc_next =
    ({8{jump }} & arg)
  | ({8{fetch}} & pc + 8'd1)
  | ({8{boot }} & BOOT_ADDR)
  | ({8{stay }} & pc);

dffr #(8) pc_dff (
  .dnxt(pc_next),
  .qout(pc),
  .clk(clk),
  .rst_n(rst_n)
);

wire load;
wire irq;
assign load = sleep_instr & ~sleep;
timer timer0 (
  .set(arg),
  .load(load),
  .irq(irq),
  .clk(clk),
  .rst_n(rst_n)
);

assign sig_clean = var[SIG_REG] == 1;
assign sig_rinse = var[SIG_REG] == 2;
assign sig_dry   = var[SIG_REG] == 3;
assign sig_done  = var[SIG_REG] == 4;

endmodule

rom.v
module rom # (
  parameter INSTRS_WIDTH = 32,
  parameter ADDR_WIDTH = 8,
  parameter ROM_SIZE = 32
) (
  input    [ADDR_WIDTH-1:0] pc,
  output [INSTRS_WIDTH-1:0] instr
);

reg [INSTRS_WIDTH-1:0] mem [0:ROM_SIZE-1];

assign instr = mem[pc];

localparam op_halt    = 8'h00;
localparam op_wait    = 8'h11;
localparam op_fill    = 8'h12;
localparam op_release = 8'h13;
localparam op_forward = 8'h14;
localparam op_reverse = 8'h15;
localparam op_set     = 8'h21;
localparam op_dec     = 8'h22;
localparam op_j       = 8'h30;
localparam op_jz      = 8'h31;
localparam op_jnz     = 8'h32;

integer i;
initial begin
  for (i = 0; i < 64; i++)
    mem[i] = 32'h0000;

  // clean start
  mem[02] = {16'd0001, 8'd02, op_set};
  mem[03] = {16'd0100, 8'd00, op_fill};
  mem[04] = {16'd0050, 8'd00, op_wait};
  mem[05] = {16'd0005, 8'd00, op_set};
  // loop 0 start
  mem[06] = {16'd0020, 8'd00, op_forward};
  mem[07] = {16'd0010, 8'd00, op_wait};
  mem[08] = {16'd0020, 8'd00, op_reverse};
  mem[09] = {16'd0010, 8'd00, op_wait};
  mem[10] = {16'd0000, 8'd00, op_dec};
  mem[11] = {16'd0006, 8'd00, op_jnz};
  // loop 0 end
  mem[12] = {16'd0100, 8'd00, op_release};
  // clean end

  // rinse start
  mem[13] = {16'd0002, 8'd02, op_set};
  mem[14] = {16'd0003, 8'd00, op_set};
  // loop 0 start
  mem[15] = {16'd0100, 8'd00, op_fill};
  mem[16] = {16'd0005, 8'd01, op_set};
  // loop 1 start
  mem[17] = {16'd0020, 8'd00, op_forward};
  mem[18] = {16'd0010, 8'd00, op_wait};
  mem[19] = {16'd0020, 8'd00, op_reverse};
  mem[20] = {16'd0010, 8'd00, op_wait};
  mem[21] = {16'd0000, 8'd01, op_dec};
  mem[22] = {16'd0017, 8'd01, op_jnz};
  // loop 1 end
  mem[23] = {16'd0100, 8'd00, op_release};
  mem[24] = {16'd0000, 8'd00, op_dec};
  mem[25] = {16'd0015, 8'd00, op_jnz};
  // loop 0 end
  // rinse end

  // dry start
  mem[26] = {16'd0003, 8'd02, op_set};
  mem[27] = {16'd0200, 8'd00, op_forward};
  // dry end
  // back to addr 0
  mem[28] = {16'd0004, 8'd02, op_set};
end

endmodule

reg_machine.v
module reg_machine # (
  parameter INSTRS_WIDTH = 32,
  parameter ADDR_WIDTH = 8
) (
  input start,

  output ctrl_fill,
  output ctrl_release,
  output ctrl_forward,
  output ctrl_reverse,

  output sig_clean,
  output sig_rinse,
  output sig_dry,
  output sig_done,

  input clk,
  input rst_n
);

wire [ADDR_WIDTH-1:0] pc;
wire [INSTRS_WIDTH-1:0] instr;

rom rom0 (
  .pc(pc),
  .instr(instr)
);

processor processor0 (
  .ena(1'b1),
  .start(start),
  .instr(instr),
  .pc(pc),
  .ctrl_fill(ctrl_fill),
  .ctrl_release(ctrl_release),
  .ctrl_forward(ctrl_forward),
  .ctrl_reverse(ctrl_reverse),
  .sig_clean(sig_clean),
  .sig_rinse(sig_rinse),
  .sig_dry(sig_dry),
  .sig_done(sig_done),
  .clk(clk),
  .rst_n(rst_n)
);

endmodule

reg_machine_test.v
`timescale 100ms/1ns
module reg_machine_test;

reg clk;
reg rst_n;

initial begin
    $dumpfile("reg_machine_test.vcd");
    $dumpvars(0, reg_machine_test);
end

always #(0.5)
  clk = ~clk;

initial begin
  clk <= 1'b0;
  rst_n <= 1'b0;
  #(2) rst_n <= 1'b1;
end

reg start = 1'd0;
wire ctrl_fill;
wire ctrl_release;
wire ctrl_forward;
wire ctrl_reverse;
wire sig_clean;
wire sig_rinse;
wire sig_dry;
wire sig_done;

reg_machine reg_machine0 (
  .start(start),
  .ctrl_fill(ctrl_fill),
  .ctrl_release(ctrl_release),
  .ctrl_forward(ctrl_forward),
  .ctrl_reverse(ctrl_reverse),
  .sig_clean(sig_clean),
  .sig_rinse(sig_rinse),
  .sig_dry(sig_dry),
  .sig_done(sig_done),
  .clk(clk),
  .rst_n(rst_n)
);

initial begin
  #(128) start <= 1'b1;
  #(2) start <= 1'b0;
  #(64) start <= 1'b1;
  #(2) start <= 1'b0;
  #(3072) rst_n <= 1'b0;
  #(1) rst_n <= 1'b1;
  #(1024) $finish;
end

endmodule

reg_machine_test.vcd
$date
	Thu Mar  2 21:27:50 2023
$end
$version
	Icarus Verilog
$end
$timescale
	1ns
$end
$scope module reg_machine_test $end
$var wire 1 ! sig_rinse $end
$var wire 1 " sig_dry $end
$var wire 1 # sig_done $end
$var wire 1 $ sig_clean $end
$var wire 1 % ctrl_reverse $end
$var wire 1 & ctrl_release $end
$var wire 1 ' ctrl_forward $end
$var wire 1 ( ctrl_fill $end
$var reg 1 ) clk $end
$var reg 1 * rst_n $end
$var reg 1 + start $end
$scope module reg_machine0 $end
$var wire 1 ) clk $end
$var wire 1 * rst_n $end
$var wire 1 + start $end
$var wire 1 ! sig_rinse $end
$var wire 1 " sig_dry $end
$var wire 1 # sig_done $end
$var wire 1 $ sig_clean $end
$var wire 8 , pc [7:0] $end
$var wire 32 - instr [31:0] $end
$var wire 1 % ctrl_reverse $end
$var wire 1 & ctrl_release $end
$var wire 1 ' ctrl_forward $end
$var wire 1 ( ctrl_fill $end
$scope module processor0 $end
$var wire 1 . active_exit_ena $end
$var wire 1 / boot $end
$var wire 1 ) clk $end
$var wire 1 ( ctrl_fill $end
$var wire 1 ' ctrl_forward $end
$var wire 1 & ctrl_release $end
$var wire 1 % ctrl_reverse $end
$var wire 1 0 ena $end
$var wire 1 1 fetch $end
$var wire 1 2 jump $end
$var wire 1 3 keep_state $end
$var wire 1 4 load $end
$var wire 1 * rst_n $end
$var wire 1 5 sleep_exit_ena $end
$var wire 1 6 sleep_next $end
$var wire 1 + start $end
$var wire 1 7 stay $end
$var wire 1 8 sleep_instr $end
$var wire 1 9 sleep $end
$var wire 1 ! sig_rinse $end
$var wire 1 " sig_dry $end
$var wire 1 # sig_done $end
$var wire 1 $ sig_clean $end
$var wire 8 : reg_id [7:0] $end
$var wire 8 ; pc_next [7:0] $end
$var wire 8 < pc [7:0] $end
$var wire 8 = opcode [7:0] $end
$var wire 1 > op_is_wait $end
$var wire 1 ? op_is_set $end
$var wire 1 @ op_is_reverse $end
$var wire 1 A op_is_release $end
$var wire 1 B op_is_jz $end
$var wire 1 C op_is_jnz $end
$var wire 1 D op_is_j $end
$var wire 1 E op_is_halt $end
$var wire 1 F op_is_forward $end
$var wire 1 G op_is_fill $end
$var wire 1 H op_is_dec $end
$var wire 1 I irq $end
$var wire 32 J instr [31:0] $end
$var wire 16 K arg [15:0] $end
$scope begin var_loop[0] $end
$scope module var_dff $end
$var wire 1 ) clk $end
$var wire 16 L dnxt [15:0] $end
$var wire 1 * rst_n $end
$var wire 16 M qout [15:0] $end
$var reg 16 N qout_r [15:0] $end
$scope begin DFFR_PROC $end
$upscope $end
$upscope $end
$upscope $end
$scope begin var_loop[1] $end
$scope module var_dff $end
$var wire 1 ) clk $end
$var wire 16 O dnxt [15:0] $end
$var wire 1 * rst_n $end
$var wire 16 P qout [15:0] $end
$var reg 16 Q qout_r [15:0] $end
$scope begin DFFR_PROC $end
$upscope $end
$upscope $end
$upscope $end
$scope begin var_loop[2] $end
$scope module var_dff $end
$var wire 1 ) clk $end
$var wire 16 R dnxt [15:0] $end
$var wire 1 * rst_n $end
$var wire 16 S qout [15:0] $end
$var reg 16 T qout_r [15:0] $end
$scope begin DFFR_PROC $end
$upscope $end
$upscope $end
$upscope $end
$scope module pc_dff $end
$var wire 1 ) clk $end
$var wire 8 U dnxt [7:0] $end
$var wire 1 * rst_n $end
$var wire 8 V qout [7:0] $end
$var reg 8 W qout_r [7:0] $end
$scope begin DFFR_PROC $end
$upscope $end
$upscope $end
$scope module sleep_dff $end
$var wire 1 ) clk $end
$var wire 1 6 dnxt $end
$var wire 1 * rst_n $end
$var wire 1 9 qout $end
$var reg 1 9 qout_r $end
$scope begin DFFR_PROC $end
$upscope $end
$upscope $end
$scope module timer0 $end
$var wire 1 ) clk $end
$var wire 17 X cnt_next [16:0] $end
$var wire 17 Y cnt_next_or_load [16:0] $end
$var wire 1 4 load $end
$var wire 1 * rst_n $end
$var wire 16 Z set [15:0] $end
$var wire 1 [ sign $end
$var wire 17 \ set_ext [16:0] $end
$var wire 1 I irq $end
$var wire 17 ] cnt [16:0] $end
$scope module timer_dff $end
$var wire 1 ) clk $end
$var wire 17 ^ dnxt [16:0] $end
$var wire 1 * rst_n $end
$var wire 17 _ qout [16:0] $end
$var reg 17 ` qout_r [16:0] $end
$scope begin DFFRS_PROC $end
$upscope $end
$upscope $end
$upscope $end
$upscope $end
$scope module rom0 $end
$var wire 32 a instr [31:0] $end
$var wire 8 b pc [7:0] $end
$var integer 32 c i [31:0] $end
$upscope $end
$upscope $end
$upscope $end
$enddefinitions $end
#0
$dumpvars
b1000000 c
b0 b
b0 a
b11111111111111111 `
b11111111111111111 _
b11111111111111111 ^
b11111111111111111 ]
b0 \
1[
b0 Z
b11111111111111111 Y
b11111111111111111 X
b0 W
b0 V
b0 U
b0 T
b0 S
b0 R
b0 Q
b0 P
b0 O
b0 N
b0 M
b0 L
b0 K
b0 J
0I
0H
0G
0F
1E
0D
0C
0B
0A
0@
0?
0>
b0 =
b0 <
b0 ;
b0 :
09
08
17
06
05
04
13
02
01
10
0/
0.
b0 -
b0 ,
0+
0*
0)
0(
0'
0&
0%
0$
0#
0"
0!
$end
#50000000
1)
#100000000
0)
#150000000
1)
#200000000
1*
0)
#250000000
1)
#300000000
0)
#350000000
1)
#400000000
0)
#450000000
1)
#500000000
0)
#550000000
1)
#600000000
0)
#650000000
1)
#700000000
0)
#750000000
1)
#800000000
0)
#850000000
1)
#900000000
0)
#950000000
1)
#1000000000
0)
#1050000000
1)
#1100000000
0)
#1150000000
1)
#1200000000
0)
#1250000000
1)
#1300000000
0)
#1350000000
1)
#1400000000
0)
#1450000000
1)
#1500000000
0)
#1550000000
1)
#1600000000
0)
#1650000000
1)
#1700000000
0)
#1750000000
1)
#1800000000
0)
#1850000000
1)
#1900000000
0)
#1950000000
1)
#2000000000
0)
#2050000000
1)
#2100000000
0)
#2150000000
1)
#2200000000
0)
#2250000000
1)
#2300000000
0)
#2350000000
1)
#2400000000
0)
#2450000000
1)
#2500000000
0)
#2550000000
1)
#2600000000
0)
#2650000000
1)
#2700000000
0)
#2750000000
1)
#2800000000
0)
#2850000000
1)
#2900000000
0)
#2950000000
1)
#3000000000
0)
#3050000000
1)
#3100000000
0)
#3150000000
1)
#3200000000
0)
#3250000000
1)
#3300000000
0)
#3350000000
1)
#3400000000
0)
#3450000000
1)
#3500000000
0)
#3550000000
1)
#3600000000
0)
#3650000000
1)
#3700000000
0)
#3750000000
1)
#3800000000
0)
#3850000000
1)
#3900000000
0)
#3950000000
1)
#4000000000
0)
#4050000000
1)
#4100000000
0)
#4150000000
1)
#4200000000
0)
#4250000000
1)
#4300000000
0)
#4350000000
1)
#4400000000
0)
#4450000000
1)
#4500000000
0)
#4550000000
1)
#4600000000
0)
#4650000000
1)
#4700000000
0)
#4750000000
1)
#4800000000
0)
#4850000000
1)
#4900000000
0)
#4950000000
1)
#5000000000
0)
#5050000000
1)
#5100000000
0)
#5150000000
1)
#5200000000
0)
#5250000000
1)
#5300000000
0)
#5350000000
1)
#5400000000
0)
#5450000000
1)
#5500000000
0)
#5550000000
1)
#5600000000
0)
#5650000000
1)
#5700000000
0)
#5750000000
1)
#5800000000
0)
#5850000000
1)
#5900000000
0)
#5950000000
1)
#6000000000
0)
#6050000000
1)
#6100000000
0)
#6150000000
1)
#6200000000
0)
#6250000000
1)
#6300000000
0)
#6350000000
1)
#6400000000
0)
#6450000000
1)
#6500000000
0)
#6550000000
1)
#6600000000
0)
#6650000000
1)
#6700000000
0)
#6750000000
1)
#6800000000
0)
#6850000000
1)
#6900000000
0)
#6950000000
1)
#7000000000
0)
#7050000000
1)
#7100000000
0)
#7150000000
1)
#7200000000
0)
#7250000000
1)
#7300000000
0)
#7350000000
1)
#7400000000
0)
#7450000000
1)
#7500000000
0)
#7550000000
1)
#7600000000
0)
#7650000000
1)
#7700000000
0)
#7750000000
1)
#7800000000
0)
#7850000000
1)
#7900000000
0)
#7950000000
1)
#8000000000
0)
#8050000000
1)
#8100000000
0)
#8150000000
1)
#8200000000
0)
#8250000000
1)
#8300000000
0)
#8350000000
1)
#8400000000
0)
#8450000000
1)
#8500000000
0)
#8550000000
1)
#8600000000
0)
#8650000000
1)
#8700000000
0)
#8750000000
1)
#8800000000
0)
#8850000000
1)
#8900000000
0)
#8950000000
1)
#9000000000
0)
#9050000000
1)
#9100000000
0)
#9150000000
1)
#9200000000
0)
#9250000000
1)
#9300000000
0)
#9350000000
1)
#9400000000
0)
#9450000000
1)
#9500000000
0)
#9550000000
1)
#9600000000
0)
#9650000000
1)
#9700000000
0)
#9750000000
1)
#9800000000
0)
#9850000000
1)
#9900000000
0)
#9950000000
1)
#10000000000
0)
#10050000000
1)
#10100000000
0)
#10150000000
1)
#10200000000
0)
#10250000000
1)
#10300000000
0)
#10350000000
1)
#10400000000
0)
#10450000000
1)
#10500000000
0)
#10550000000
1)
#10600000000
0)
#10650000000
1)
#10700000000
0)
#10750000000
1)
#10800000000
0)
#10850000000
1)
#10900000000
0)
#10950000000
1)
#11000000000
0)
#11050000000
1)
#11100000000
0)
#11150000000
1)
#11200000000
0)
#11250000000
1)
#11300000000
0)
#11350000000
1)
#11400000000
0)
#11450000000
1)
#11500000000
0)
#11550000000
1)
#11600000000
0)
#11650000000
1)
#11700000000
0)
#11750000000
1)
#11800000000
0)
#11850000000
1)
#11900000000
0)
#11950000000
1)
#12000000000
0)
#12050000000
1)
#12100000000
0)
#12150000000
1)
#12200000000
0)
#12250000000
1)
#12300000000
0)
#12350000000
1)
#12400000000
0)
#12450000000
1)
#12500000000
0)
#12550000000
1)
#12600000000
0)
#12650000000
1)
#12700000000
0)
#12750000000
1)
#12800000000
b10 ;
b10 U
07
1/
1+
0)
#12850000000
b11 ;
b11 U
b1 R
07
11
0/
b1 \
b1 K
b1 Z
b10 :
1?
0E
b100001 =
b10000001000100001 -
b10000001000100001 J
b10000001000100001 a
b10 ,
b10 <
b10 V
b10 W
b10 b
1)
#12900000000
0)
#12950000000
17
b1100100 Y
b1100100 ^
01
16
03
b11 ;
b11 U
b1 R
14
1.
18
1(
b1100100 \
b1100100 K
b1100100 Z
b0 :
0?
1G
b10010 =
b11001000000000000010010 -
b11001000000000000010010 J
b11001000000000000010010 a
b11 ,
b11 <
b11 V
b11 W
b11 b
1$
b1 S
b1 T
1)
#13000000000
0+
0)
#13050000000
16
b1100011 Y
b1100011 ^
13
b1100011 X
04
0.
0[
b1100100 ]
b1100100 _
b1100100 `
19
1)
#13100000000
0)
#13150000000
b1100010 Y
b1100010 ^
b1100010 X
b1100011 ]
b1100011 _
b1100011 `
1)
#13200000000
0)
#13250000000
b1100001 Y
b1100001 ^
b1100001 X
b1100010 ]
b1100010 _
b1100010 `
1)
#13300000000
0)
#13350000000
b1100000 Y
b1100000 ^
b1100000 X
b1100001 ]
b1100001 _
b1100001 `
1)
#13400000000
0)
#13450000000
b1011111 Y
b1011111 ^
b1011111 X
b1100000 ]
b1100000 _
b1100000 `
1)
#13500000000
0)
#13550000000
b1011110 Y
b1011110 ^
b1011110 X
b1011111 ]
b1011111 _
b1011111 `
1)
#13600000000
0)
#13650000000
b1011101 Y
b1011101 ^
b1011101 X
b1011110 ]
b1011110 _
b1011110 `
1)
#13700000000
0)
#13750000000
b1011100 Y
b1011100 ^
b1011100 X
b1011101 ]
b1011101 _
b1011101 `
1)
#13800000000
0)
#13850000000
b1011011 Y
b1011011 ^
b1011011 X
b1011100 ]
b1011100 _
b1011100 `
1)
#13900000000
0)
#13950000000
b1011010 Y
b1011010 ^
b1011010 X
b1011011 ]
b1011011 _
b1011011 `
1)
#14000000000
0)
#14050000000
b1011001 Y
b1011001 ^
b1011001 X
b1011010 ]
b1011010 _
b1011010 `
1)
#14100000000
0)
#14150000000
b1011000 Y
b1011000 ^
b1011000 X
b1011001 ]
b1011001 _
b1011001 `
1)
#14200000000
0)
#14250000000
b1010111 Y
b1010111 ^
b1010111 X
b1011000 ]
b1011000 _
b1011000 `
1)
#14300000000
0)
#14350000000
b1010110 Y
b1010110 ^
b1010110 X
b1010111 ]
b1010111 _
b1010111 `
1)
#14400000000
0)
#14450000000
b1010101 Y
b1010101 ^
b1010101 X
b1010110 ]
b1010110 _
b1010110 `
1)
#14500000000
0)
#14550000000
b1010100 Y
b1010100 ^
b1010100 X
b1010101 ]
b1010101 _
b1010101 `
1)
#14600000000
0)
#14650000000
b1010011 Y
b1010011 ^
b1010011 X
b1010100 ]
b1010100 _
b1010100 `
1)
#14700000000
0)
#14750000000
b1010010 Y
b1010010 ^
b1010010 X
b1010011 ]
b1010011 _
b1010011 `
1)
#14800000000
0)
#14850000000
b1010001 Y
b1010001 ^
b1010001 X
b1010010 ]
b1010010 _
b1010010 `
1)
#14900000000
0)
#14950000000
b1010000 Y
b1010000 ^
b1010000 X
b1010001 ]
b1010001 _
b1010001 `
1)
#15000000000
0)
#15050000000
b1001111 Y
b1001111 ^
b1001111 X
b1010000 ]
b1010000 _
b1010000 `
1)
#15100000000
0)
#15150000000
b1001110 Y
b1001110 ^
b1001110 X
b1001111 ]
b1001111 _
b1001111 `
1)
#15200000000
0)
#15250000000
b1001101 Y
b1001101 ^
b1001101 X
b1001110 ]
b1001110 _
b1001110 `
1)
#15300000000
0)
#15350000000
b1001100 Y
b1001100 ^
b1001100 X
b1001101 ]
b1001101 _
b1001101 `
1)
#15400000000
0)
#15450000000
b1001011 Y
b1001011 ^
b1001011 X
b1001100 ]
b1001100 _
b1001100 `
1)
#15500000000
0)
#15550000000
b1001010 Y
b1001010 ^
b1001010 X
b1001011 ]
b1001011 _
b1001011 `
1)
#15600000000
0)
#15650000000
b1001001 Y
b1001001 ^
b1001001 X
b1001010 ]
b1001010 _
b1001010 `
1)
#15700000000
0)
#15750000000
b1001000 Y
b1001000 ^
b1001000 X
b1001001 ]
b1001001 _
b1001001 `
1)
#15800000000
0)
#15850000000
b1000111 Y
b1000111 ^
b1000111 X
b1001000 ]
b1001000 _
b1001000 `
1)
#15900000000
0)
#15950000000
b1000110 Y
b1000110 ^
b1000110 X
b1000111 ]
b1000111 _
b1000111 `
1)
#16000000000
0)
#16050000000
b1000101 Y
b1000101 ^
b1000101 X
b1000110 ]
b1000110 _
b1000110 `
1)
#16100000000
0)
#16150000000
b1000100 Y
b1000100 ^
b1000100 X
b1000101 ]
b1000101 _
b1000101 `
1)
#16200000000
0)
#16250000000
b1000011 Y
b1000011 ^
b1000011 X
b1000100 ]
b1000100 _
b1000100 `
1)
#16300000000
0)
#16350000000
b1000010 Y
b1000010 ^
b1000010 X
b1000011 ]
b1000011 _
b1000011 `
1)
#16400000000
0)
#16450000000
b1000001 Y
b1000001 ^
b1000001 X
b1000010 ]
b1000010 _
b1000010 `
1)
#16500000000
0)
#16550000000
b1000000 Y
b1000000 ^
b1000000 X
b1000001 ]
b1000001 _
b1000001 `
1)
#16600000000
0)
#16650000000
b111111 Y
b111111 ^
b111111 X
b1000000 ]
b1000000 _
b1000000 `
1)
#16700000000
0)
#16750000000
b111110 Y
b111110 ^
b111110 X
b111111 ]
b111111 _
b111111 `
1)
#16800000000
0)
#16850000000
b111101 Y
b111101 ^
b111101 X
b111110 ]
b111110 _
b111110 `
1)
#16900000000
0)
#16950000000
b111100 Y
b111100 ^
b111100 X
b111101 ]
b111101 _
b111101 `
1)
#17000000000
0)
#17050000000
b111011 Y
b111011 ^
b111011 X
b111100 ]
b111100 _
b111100 `
1)
#17100000000
0)
#17150000000
b111010 Y
b111010 ^
b111010 X
b111011 ]
b111011 _
b111011 `
1)
#17200000000
0)
#17250000000
b111001 Y
b111001 ^
b111001 X
b111010 ]
b111010 _
b111010 `
1)
#17300000000
0)
#17350000000
b111000 Y
b111000 ^
b111000 X
b111001 ]
b111001 _
b111001 `
1)
#17400000000
0)
#17450000000
b110111 Y
b110111 ^
b110111 X
b111000 ]
b111000 _
b111000 `
1)
#17500000000
0)
#17550000000
b110110 Y
b110110 ^
b110110 X
b110111 ]
b110111 _
b110111 `
1)
#17600000000
0)
#17650000000
b110101 Y
b110101 ^
b110101 X
b110110 ]
b110110 _
b110110 `
1)
#17700000000
0)
#17750000000
b110100 Y
b110100 ^
b110100 X
b110101 ]
b110101 _
b110101 `
1)
#17800000000
0)
#17850000000
b110011 Y
b110011 ^
b110011 X
b110100 ]
b110100 _
b110100 `
1)
#17900000000
0)
#17950000000
b110010 Y
b110010 ^
b110010 X
b110011 ]
b110011 _
b110011 `
1)
#18000000000
0)
#18050000000
b110001 Y
b110001 ^
b110001 X
b110010 ]
b110010 _
b110010 `
1)
#18100000000
0)
#18150000000
b110000 Y
b110000 ^
b110000 X
b110001 ]
b110001 _
b110001 `
1)
#18200000000
0)
#18250000000
b101111 Y
b101111 ^
b101111 X
b110000 ]
b110000 _
b110000 `
1)
#18300000000
0)
#18350000000
b101110 Y
b101110 ^
b101110 X
b101111 ]
b101111 _
b101111 `
1)
#18400000000
0)
#18450000000
b101101 Y
b101101 ^
b101101 X
b101110 ]
b101110 _
b101110 `
1)
#18500000000
0)
#18550000000
b101100 Y
b101100 ^
b101100 X
b101101 ]
b101101 _
b101101 `
1)
#18600000000
0)
#18650000000
b101011 Y
b101011 ^
b101011 X
b101100 ]
b101100 _
b101100 `
1)
#18700000000
0)
