rom.v
module rom (
  input   [7:0] pc,
  output [15:0] instr
);

reg [15:0] mem [0:64];

assign instr = mem[pc];

localparam op_halt    = 8'h00;
localparam op_wait    = 8'h01;
localparam op_fill    = 8'h02;
localparam op_release = 8'h03;
localparam op_forward = 8'h04;
localparam op_reverse = 8'h05;
localparam op_set     = 8'h11;
localparam op_dec     = 8'h12;
localparam op_jz      = 8'h21;
localparam op_jnz     = 8'h22;

integer i;
initial begin
  for (i = 0; i < 64; i++)
    mem[i] = 16'h0000;

  mem[02] = {8'd100, op_fill};
  mem[03] = {8'd050, op_wait};
  mem[04] = {8'd005, op_set};
  // loop start
  mem[05] = {8'd020, op_forward};
  mem[06] = {8'd010, op_wait};
  mem[07] = {8'd020, op_reverse};
  mem[08] = {8'd010, op_wait};
  mem[09] = {8'd000, op_dec};
  mem[10] = {8'd005, op_jnz};
  // loop end
  mem[11] = {8'd100, op_release};
end

endmodule

rom_test.v
`timescale 1s/1ms
module rom_test;

initial begin
    $dumpfile("rom_test.vcd");
    $dumpvars(0, rom_test);
end

reg [7:0] pc;
wire [15:0] instr;

rom rom0 (
  .pc(pc),
  .instr(instr)
);

initial begin
  pc = 8'h00;
  #(1) pc = 8'h02;
  #(1) pc = 8'h03;
  #(1) pc = 8'h04;
  #(1) pc = 8'h05;
  #(1) pc = 8'h06;
  #(1) pc = 8'h07;
  #(1) pc = 8'h08;
  #(1) pc = 8'h02;
  #(1) pc = 8'h03;
  #(1) pc = 8'h04;
  #(1) $finish;
end

endmodule

rom_test.vcd
$date
	Thu Mar  2 17:07:28 2023
$end
$version
	Icarus Verilog
$end
$timescale
	1ms
$end
$scope module rom_test $end
$var wire 16 ! instr [15:0] $end
$var reg 8 " pc [7:0] $end
$scope module rom0 $end
$var wire 16 # instr [15:0] $end
$var wire 8 $ pc [7:0] $end
$var integer 32 % i [31:0] $end
$upscope $end
$upscope $end
$enddefinitions $end
#0
$dumpvars
b1000000 %
b0 $
b0 #
b0 "
b0 !
$end
#1000
b11000010001 !
b11000010001 #
b10 "
b10 $
#2000
b10100000100 !
b10100000100 #
b11 "
b11 $
#3000
b1000000001 !
b1000000001 #
b100 "
b100 $
#4000
b10100000101 !
b10100000101 #
b101 "
b101 $
#5000
b1000000001 !
b1000000001 #
b110 "
b110 $
#6000
b10010 !
b10010 #
b111 "
b111 $
#7000
b1000100001 !
b1000100001 #
b1000 "
b1000 $
#8000
b11000010001 !
b11000010001 #
b10 "
b10 $
#9000
b10100000100 !
b10100000100 #
b11 "
b11 $
#10000
b1000000001 !
b1000000001 #
b100 "
b100 $
