dff.v
// ===========================================================================
//
// Description:
//  Verilog module sirv_gnrl DFF with Load-enable and Reset
//  Default reset value is 1
//
// ===========================================================================
module dfflrs # (
  parameter DW = 32
) (

  input               lden, 
  input      [DW-1:0] dnxt,
  output     [DW-1:0] qout,

  input               clk,
  input               rst_n
);

reg [DW-1:0] qout_r;

always @(posedge clk or negedge rst_n)
begin : DFFLRS_PROC
  if (rst_n == 1'b0)
    qout_r <= {DW{1'b1}};
  else if (lden == 1'b1)
    qout_r <= dnxt;
end

assign qout = qout_r;


endmodule
// ===========================================================================
//
// Description:
//  Verilog module sirv_gnrl DFF with Load-enable and Reset
//  Default reset value is 0
//
// ===========================================================================

module dfflr # (
  parameter DW = 32
) (

  input               lden, 
  input      [DW-1:0] dnxt,
  output     [DW-1:0] qout,

  input               clk,
  input               rst_n
);

reg [DW-1:0] qout_r;

always @(posedge clk or negedge rst_n)
begin : DFFLR_PROC
  if (rst_n == 1'b0)
    qout_r <= {DW{1'b0}};
  else if (lden == 1'b1)
    qout_r <= #1 dnxt;
end

assign qout = qout_r;


endmodule
// ===========================================================================
//
// Description:
//  Verilog module sirv_gnrl DFF with Load-enable, no reset 
//
// ===========================================================================

module dffl # (
  parameter DW = 32
) (

  input               lden, 
  input      [DW-1:0] dnxt,
  output     [DW-1:0] qout,

  input               clk 
);

reg [DW-1:0] qout_r;

always @(posedge clk)
begin : DFFL_PROC
  if (lden == 1'b1)
    qout_r <= #1 dnxt;
end

assign qout = qout_r;


endmodule
// ===========================================================================
//
// Description:
//  Verilog module sirv_gnrl DFF with Reset, no load-enable
//  Default reset value is 1
//
// ===========================================================================

module dffrs # (
  parameter DW = 32
) (

  input      [DW-1:0] dnxt,
  output     [DW-1:0] qout,

  input               clk,
  input               rst_n
);

reg [DW-1:0] qout_r;

always @(posedge clk or negedge rst_n)
begin : DFFRS_PROC
  if (rst_n == 1'b0)
    qout_r <= {DW{1'b1}};
  else                  
    qout_r <= dnxt;
end

assign qout = qout_r;

endmodule
// ===========================================================================
//
// Description:
//  Verilog module sirv_gnrl DFF with Reset, no load-enable
//  Default reset value is 0
//
// ===========================================================================

module dffr # (
  parameter DW = 32
) (

  input      [DW-1:0] dnxt,
  output     [DW-1:0] qout,

  input               clk,
  input               rst_n
);

reg [DW-1:0] qout_r;

always @(posedge clk or negedge rst_n)
begin : DFFR_PROC
  if (rst_n == 1'b0)
    qout_r <= {DW{1'b0}};
  else                  
    qout_r <= dnxt;
end

assign qout = qout_r;

endmodule
// ===========================================================================
//
// Description:
//  Verilog module for general latch 
//
// ===========================================================================

module sirv_gnrl_ltch # (
  parameter DW = 32
) (

  //input               test_mode,
  input               lden, 
  input      [DW-1:0] dnxt,
  output     [DW-1:0] qout
);

reg [DW-1:0] qout_r;

always @ (*) 
begin : LTCH_PROC
  if (lden == 1'b1)
    qout_r <= dnxt;
end

//assign qout = test_mode ? dnxt : qout_r;
assign qout = qout_r;


endmodule

timer.v
module timer (
  input [7:0] set,
  input       load,
  output      irq,

  input clk,
  input rst_n
);

wire [8:0] cnt;
wire [8:0] cnt_next;
wire [8:0] cnt_next_or_load;
wire sign = cnt[8];

assign irq = cnt == 9'd0;

wire [8:0] set_ext;
assign set_ext = {1'b0, set};

assign cnt_next =
    ({9{~sign}} & (cnt - 9'd1))
  | ({9{ sign}} & 9'h1ff);

assign cnt_next_or_load =
    ({9{ load}} & set_ext)
  | ({9{~load}} & cnt_next);

dffrs #(9) timer_dff (
  .dnxt(cnt_next_or_load),
  .qout(cnt),
  .clk(clk),
  .rst_n(rst_n)
);

endmodule

timer_test.v
`timescale 1s/1ms
module timer_test;

reg clk;
reg rst_n;

initial begin
    $dumpfile("timer_test.vcd");
    $dumpvars(0, timer_test);
end

always #(0.5)
  clk = ~clk;

initial begin
  clk <= 1'b0;
  rst_n <= 1'b0;
  #(1) rst_n <= 1'b1;
end

reg [7:0] set;
reg       load = 1'b0;
wire      irq;

timer timer0 (
  .set(set),
  .load(load),
  .irq(irq),
  .clk(clk),
  .rst_n(rst_n)
);

initial begin
  #(2)
  set <= 8'd7;
  #(1)
  load <= 1'b1;
  #(1)
  load <= 1'b0;
  #(12)
  $finish;
end

endmodule

timer_test.vcd
$date
	Thu Mar  2 14:35:44 2023
$end
$version
	Icarus Verilog
$end
$timescale
	1ms
$end
$scope module timer_test $end
$var wire 1 ! irq $end
$var reg 1 " clk $end
$var reg 1 # load $end
$var reg 1 $ rst_n $end
$var reg 8 % set [7:0] $end
$scope module timer0 $end
$var wire 1 " clk $end
$var wire 9 & cnt_next [8:0] $end
$var wire 9 ' cnt_next_or_load [8:0] $end
$var wire 1 # load $end
$var wire 1 $ rst_n $end
$var wire 8 ( set [7:0] $end
$var wire 1 ) sign $end
$var wire 9 * set_ext [8:0] $end
$var wire 1 ! irq $end
$var wire 9 + cnt [8:0] $end
$scope module timer_dff $end
$var wire 1 " clk $end
$var wire 9 , dnxt [8:0] $end
$var wire 1 $ rst_n $end
$var wire 9 - qout [8:0] $end
$var reg 9 . qout_r [8:0] $end
$scope begin DFFRS_PROC $end
$upscope $end
$upscope $end
$upscope $end
$upscope $end
$enddefinitions $end
#0
$dumpvars
b111111111 .
b111111111 -
b111111111 ,
b111111111 +
b0xxxxxxxx *
1)
bx (
b111111111 '
b111111111 &
bx %
0$
0#
0"
0!
$end
#500
1"
#1000
1$
0"
#1500
1"
#2000
b111 *
b111 %
b111 (
0"
#2500
1"
#3000
b111 '
b111 ,
1#
0"
#3500
b110 &
0)
b111 +
b111 -
b111 .
1"
#4000
b110 '
b110 ,
0#
0"
#4500
b101 '
b101 ,
b101 &
b110 +
b110 -
b110 .
1"
#5000
0"
#5500
b100 '
b100 ,
b100 &
b101 +
b101 -
b101 .
1"
#6000
0"
#6500
b11 '
b11 ,
b11 &
b100 +
b100 -
b100 .
1"
#7000
0"
#7500
b10 '
b10 ,
b10 &
b11 +
b11 -
b11 .
1"
#8000
0"
#8500
b1 '
b1 ,
b1 &
b10 +
b10 -
b10 .
1"
#9000
0"
#9500
b0 '
b0 ,
b0 &
b1 +
b1 -
b1 .
1"
#10000
0"
#10500
b111111111 '
b111111111 ,
b111111111 &
1!
b0 +
b0 -
b0 .
1"
#11000
0"
#11500
1)
0!
b111111111 +
b111111111 -
b111111111 .
1"
